Workbook
Name Tax_rate: [1]Model!$M$15

Sheet Temp
A1: =Historical!A1 -> Alkem Laboratories

Sheet Valuation Summary
A1: =Historical!A1 -> Alkem Laboratories
A2: Valuation Summary - Football Field
A4: Football Field Data
H6: Comps | I6: DCF | J6: 52-week hi/lo
D7: High | H7: =MAX('Relative Valuation'!L25:L27) -> 7783.6883 | I7: 5303.5 | J7: =MAX(Beta!D6:D65) -> 6170.35
D8: High | H8: =H7 -> 7783.6883 | I8: =I7 -> 5303.5 | J8: =J7 -> 6170.35
D9: Low | H9: =MIN('Relative Valuation'!L25:L27) -> 4006.6464 | I9: 4572.6077 | J9: =MIN(Beta!D6:D65) -> 2614.39
D10: Low | H10: =H9 -> 4006.6464 | I10: =I9 -> 4572.6077 | J10: =J9 -> 2614.39
A12: Valuation Summary

Sheet Historical
A1: Alkem Laboratories
A2: Historical Data
A4: INCOME STATEMENT | H4: 2019 | I4: 2020 | J4: 2021 | K4: 2022 | L4: 2023 | M4: 2024 | N4: 2025
D5: Income
D6: (a) Revenue from operations | H6: 73571.9 | I6: 83443.6 | J6: 88650.1 | K6: 106341.9 | L6: 115992.6 | M6: 126675.8 | N6: 129645.2
D7: (b) Other income | H7: 877 | I7: 1042.2 | J7: 2332.1 | K7: 1626.5 | L7: 2160.8 | M7: 3108.4 | N7: 4937.4
D8: Total income | H8: 74448.9 | I8: 84485.8 | J8: 90982.2 | K8: 107968.4 | L8: 118153.4 | M8: 129784.2 | N8: 134582.6
D9: Expenses
D10: (a) Cost of materials consumed | H10: 18111.4 | I10: 21318.3 | J10: 23945.4 | K10: 32260.6 | L10: 30569.2 | M10: 32945.9 | N10: 34403.7
D11: (b) Purchases of stock-in-trade | H11: 11301.9 | I11: 14430.6 | J11: 14377.6 | K11: 14897.1 | L11: 13875.5 | M11: 16288.7 | N11: 15140.2
D12: (c) Changes in inventories of finished goods, work-in-progress and | H12: 36.4 | I12: -2299.5 | J12: -3338.4 | K12: -5354.8 | L12: 4623.7 | M12: 141.2 | N12: -1901.3
D13: stock-in-trade
D14: (d) Employee benefits expense | H14: 13624.6 | I14: 15054.9 | J14: 16210.3 | K14: 19627.1 | L14: 21313.5 | M14: 22010.1 | N14: 24539.2
D15: (e) Finance costs | H15: 546.3 | I15: 650.6 | J15: 589.2 | K15: 523.7 | L15: 1073.6 | M15: 1124.1 | N15: 1217
D16: (f ) Depreciation and amortisation expense | H16: 1931.8 | I16: 2527.6 | J16: 2745.8 | K16: 3039.6 | L16: 3104.2 | M16: 2993 | N16: 3571.6
D17: (g) Other expenses | H17: 19349.9 | I17: 20205.4 | J17: 18031.3 | K17: 24382.7 | L17: 29516.2 | M17: 32835 | N17: 32341.9
D18: Total expenses | H18: 64902.3 | I18: 71887.9 | J18: 72561.2 | K18: 89376 | L18: 104075.9 | M18: 108338 | N18: 109312.3
D19: Profit before exceptional items and tax (1) - (2) | H19: 9546.6 | I19: 12597.9 | J19: 18421 | K19: 18592.4 | L19: 14077.5 | M19: 21446.2 | N19: 25270.3
D20: Exceptional items | H20: 0 | I20: 0 | J20: 0 | K20: -149.6 | L20: -1029.8 | M20: -1214.9 | N20: –
D21: Profit before tax (3) + (4) | H21: 9546.6 | I21: 12597.9 | J21: 18421 | K21: 18442.8 | L21: 13047.7 | M21: 20231.3 | N21: 25270.3
D22: Tax expense
D23: (a) Current tax | H23: 2291.7 | I23: 3542.5 | J23: 3965.3 | K23: 3619.8 | L23: 2739 | M23: 4222.8 | N23: 5236
D24: (b) Deferred tax charge/(credit) (net) | H24: -481.5 | I24: -2123.9 | J24: -1722 | K24: -1980.2 | L24: 240.6 | M24: -2106.1 | N24: -2125.7
D25: Tax adjustment of earlier periods | H25: 0 | I25: -313.8
D26: Total tax expenses (a + b) | H26: 1810.2 | I26: 1104.8 | J26: 2243.3 | K26: 1639.6 | L26: 2979.6 | M26: 2116.7 | N26: 3110.3
D27: Profit for the year (5) - (6) | H27: 7736.4 | I27: 11493.1 | J27: 16177.7 | K27: 16803.2 | L27: 10068.1 | M27: 18114.6 | N27: 22160
D28: Profit attributable to Non-Controlling Interest | H28: 131.3 | I28: 222.4 | J28: 327.5 | K28: 347 | L28: 226.4 | M28: 156.9 | N28: 499
D29: Profit attributable to Owners of the Company (7) - (8) | H29: 7605.1 | I29: 11270.7 | J29: 15850.2 | K29: 16456.2 | L29: 9841.7 | M29: 17957.7 | N29: 21654.8
A31: BALANCE SHEET | H31: =H4 -> 2019 | I31: =I4 -> 2020 | J31: =J4 -> 2021 | K31: =K4 -> 2022 | L31: =L4 -> 2023 | M31: =M4 -> 2024 | N31: =N4 -> 2025
D33: ASSETS
D34: Non-current assets
D35: (a) Property, plant and equipment | H35: 21056.2 | I35: 23062.9 | J35: 22339.3 | K35: 22871 | L35: 20654 | M35: 21614.6 | N35: 20639.3
D36: Right of use assets | L36: 1378.5 | M36: 2471.7 | N36: 3222.2
D37: (b) Capital work in progress | H37: 4929.6 | I37: 3629.7 | J37: 3932.8 | K37: 3394.8 | L37: 3102.7 | M37: 1484 | N37: 4765.5
D38: (c) Goodwill | H38: 231.5 | I38: 259.3 | J38: 3953.9 | K38: 4030.9 | L38: 4131.7 | M38: 4167.4 | N38: 4231.1
D39: (d) Other intangible assets | H39: 442.6 | I39: 2032.7 | J39: 1636.6 | K39: 2115.4 | L39: 664.1 | M39: 474.1 | N39: 430.5
D40: (e) Goodwill on consolidation | H40: 3574.1 | I40: 3725.2 | J40: 0 | K40: 0 | L40: 0 | M40: 101.7 | N40: 715.2
D41: Intangible assets under development | L41: 129.7
D42: (f) Financial assets
D43: (i) Investments | H43: 957.4 | I43: 915 | J43: 1539.5 | K43: 2316.7 | L43: 3046.1 | N43: 323.8
D44: (ii) Loans | H44: 136.3 | I44: 106.1 | J44: 80.2 | K44: 80.2 | L44: 80.2 | M44: 3348 | N44: 9108.6
D45: (iii) Other financial assets | H45: 462 | I45: 466.8 | J45: 607.9 | K45: 7106.7 | L45: 2952.5 | M45: 1202.2 | N45: 4753.6
D46: (g) Deferred tax assets (net) | H46: 7076.3 | I46: 9325.7 | J46: 11079.1 | K46: 13092.6 | L46: 13025 | M46: 15148.3 | N46: 17382.5
D47: (h) Non-current tax assets (net) | H47: 392.7 | I47: 419.5 | J47: 171.1 | K47: 533.1 | L47: 575.4 | M47: 781.7 | N47: 647.1
D48: (i) Other non-current assets | H48: 661.9 | I48: 530.1 | J48: 564 | K48: 796.2 | L48: 529.6 | M48: 839.5 | N48: 1233.4
D49: Total non-current assets | H49: 39920.6 | I49: 44473 | J49: 45904.4 | K49: 56337.6 | L49: 50269.5 | M49: 51633.2 | N49: 67452.8
D50: Current assets
D51: (a) Inventories | H51: 14998.7 | I51: 18188.2 | J51: 23124.4 | K51: 30055.3 | L51: 26075.3 | M51: 26611.8 | N51: 29224.1
D52: (b) Financial assets
D53: (i) Investments | H53: 2278.8 | I53: 1698.9 | J53: 1788.3 | K53: 1393.1 | L53: 3172.1 | M53: 1489.9 | N53: 9022.6
D54: (ii) Trade receivables | H54: 12484.1 | I54: 16493.6 | J54: 16072.1 | K54: 18846 | L54: 21321.8 | M54: 22528.1 | N54: 24662.5
D55: (iii) Cash and cash equivalents | H55: 2490.5 | I55: 1759.4 | J55: 1742.2 | K55: 2321.8 | L55: 2738 | M55: 4550.7 | N55: 3041.4
D56: (iv) Bank balances other than above | H56: 4125.5 | I56: 9162.7 | J56: 18162.3 | K56: 23464 | L56: 23430.9 | M56: 11242.8 | N56: 12589.4
D57: (v) Loans | H57: 308 | I57: 279.7 | J57: 187.3 | K57: 202.5 | L57: 67.7 | M57: 90.7 | N57: 90.4
D58: (vi) Other financial assets | H58: 1064.6 | I58: 1931 | J58: 2606 | K58: 1731.5 | L58: 1897.5 | M58: 29302 | N58: 21154.8
D59: (c) Other current assets | H59: 4293.8 | I59: 5266 | J59: 5550.1 | K59: 6322.8 | L59: 7360.9 | M59: 8299.8 | N59: 8326.7
H60: 42044 | I60: 54779.5 | J60: 69232.7 | K60: 84337 | L60: 86064.2 | M60: 104115.8 | N60: 108111.9
D61: (d) Non-current assets held for sale | H61: 117.3 | I61: 180.8 | J61: 55.5 | K61: 17.3 | L61: 1232.6 | N61: 1346.3
D62: Total current assets | H62: 42161.3 | I62: 54960.3 | J62: 69288.2 | K62: 84354.3 | L62: 87296.8 | M62: 104115.8 | N62: 109438.2
D64: TOTAL ASSETS | H64: 82081.9 | I64: 99433.3 | J64: 115192.6 | K64: 140691.9 | L64: 137566.3 | M64: 155749 | N64: 176911
D65: EQUITY AND LIABILITIES
D66: Equity
D67: (a) Equity share capital | H67: 239.1 | I67: 239.1 | J67: 239.1 | K67: 239.1 | L67: 239.1 | M67: 239.1 | N67: 239.1
D68: (b) Other equity | H68: 54154.3 | I68: 61367.6 | J68: 73528.2 | K68: 86139.9 | L68: 90213.8 | M68: 102881.5 | N68: 119609.6
D69: Equity attributable to owners of the Company | H69: 54393.4 | I69: 61606.7 | J69: 73767.3 | K69: 86379 | L69: 90452.9 | M69: 103120.6 | N69: 119848.7
D70: (c) Non-controlling interest | H70: 1326.1 | I70: 1483 | J70: 1812.8 | K70: 2094.3 | L70: 3897.1 | M70: 4023.4 | N70: 4487.6
D71: Total Equity | H71: 55719.5 | I71: 63089.7 | J71: 75580.1 | K71: 88473.3 | L71: 94350 | M71: 107144 | N71: 124336.3
D72: Liabilities
D73: Non-current liabilities
D74: (a) Financial liabilities
D75: (i) Borrowings | H75: 2313 | I75: 1592.4 | J75: 279.3 | K75: 93.8 | L75: 0 | M75: 400 | N75: 3109.1
D76: Lease liabilities | J76: 697.1 | K76: 664.7 | L76: 703.3 | M76: 1892.6 | N76: 2674.2
D77: Other financial liabilities | L77: 1660.1 | M77: 3109.9 | N77: 3539.9
D78: (b) Provisions | H78: 1737.2 | I78: 2220.4 | J78: 2507.3 | K78: 3327.5 | L78: 3693.6 | M78: 2998.6 | N78: 3382.2
D79: (c) Deferred tax liabilities (net) | H79: 3 | I79: - | L79: 0 | M79: 258.4 | N79: 219.5
D80: (d) Other non-current liabilities | H80: 133.9 | I80: 97.7 | J80: 88.3 | K80: 79.2 | L80: 88
D81: Total non-current liabilities | H81: 4187.1 | I81: 3910.5 | J81: 3572 | K81: 4165.2 | L81: 6145 | M81: 8659.5 | N81: 12924.9
D82: Current liabilities
D83: (a) Financial liabilities
D84: (i) Borrowings | H84: 6712.7 | I84: 15035.1 | J84: 16727.9 | K84: 25707.4 | L84: 13071.5 | M84: 11739.7 | N84: 7518.8
D85: (ii) Lease Liabilities | J85: 215.5 | K85: 216 | L85: 192 | M85: 151.8 | N85: 506.9
D86: (iii) Trade payables
D87: Dues of micro and small enterprises | H87: 606.3 | I87: 1025 | J87: 1189.6 | K87: 924.2 | L87: 1104.6 | M87: 670 | N87: 879.8
D88: Dues of creditors other than micro and small enterprises | H88: 9016.2 | I88: 8515.5 | J88: 9504.5 | K88: 10809.6 | L88: 10545.5 | M88: 16811.2 | N88: 17513.7
D89: (iii) Other financial liabilities | H89: 3428.7 | I89: 4519.6 | J89: 4653.9 | K89: 5993.8 | L89: 6326.9 | M89: 6457.7 | N89: 7908.1
D90: (b) Other current liabilities | H90: 852.1 | I90: 1035.1 | J90: 1193.4 | K90: 1503.2 | L90: 1868.9 | M90: 2296.5 | N90: 3120.5
D91: (c) Provisions | H91: 1538.2 | I91: 1847 | J91: 2366.4 | K91: 2736 | L91: 3727.5 | M91: 1268.7 | N91: 1591
D92: (d) Current tax liabilities (net) | H92: 21.1 | I92: 455.8 | J92: 189.3 | K92: 163.2 | L92: 234.4 | M92: 549.9 | N92: 611
D93: Total current liabilities | H93: 22175.3 | I93: 32433.1 | J93: 36040.5 | K93: 48053.4 | L93: 37071.5 | M93: 39945.5 | N93: 39649.3
D95: Total Liabilities | H95: 26362.4 | I95: 36343.6 | J95: 39612.5 | K95: 52218.6 | L95: 43216.5 | M95: 48605 | N95: 52574.1
D96: TOTAL EQUITY AND LIABILITIES | H96: 82081.9 | I96: 99433.3 | J96: 115192.6 | K96: 140691.9 | L96: 137566.5 | M96: 155749 | N96: 176911
A99: CASH FLOW STATEMENT | H99: 2019 | I99: 2020 | J99: 2021 | K99: 2022 | L99: 2023 | M99: 2024 | N99: 2025
D100: A. Cash Flow from Operating Activities:
D101: Profit before tax | H101: 9546.6 | I101: 12597.9 | J101: 18421 | K101: 18442.8 | L101: 13047.7 | M101: 20231.3 | N101: 25270.3
D102: Adjustments for:
D103: Depreciation and amortisation expense | H103: 1931.8 | I103: 2527.6 | J103: 2745.8 | K103: 3039.6 | L103: 3104.2 | M103: 2993 | N103: 3571.6
D104: Liabilities no longer required written back | J104: - | K104: -160.1 | L104: -17.5 | M104: -19.8 | N104: -155.1
D105: Profit on sale of investments | H105: -73.3 | I105: -0.8 | J105: -102.6 | K105: -33.8 | L105: -21.6 | M105: -146.3 | N105: -110.2
D106: Unrealised (gain) / loss on fair valuation of investments (net) | H106: 45.5 | I106: 172.2 | J106: -266.9 | K106: 69 | L106: -287 | M106: -5.4 | N106: -418.7
D107: Profit on sale of property plant and equipment (net) | H107: 54.8 | I107: -12.6 | J107: -37 | K107: 14.3 | L107: 123.6 | M107: 31.8 | N107: -46
...

Sheet Model
A1: =Historical!A1 -> Alkem Laboratories | H1: Historical Period | M1: Forecast Period
A2: Financial Statement & DCF Analysis | H2: =Historical!J4 -> 2021 | I2: =Historical!K4 -> 2022 | J2: =Historical!L4 -> 2023 | K2: =J2+1 -> 2024 | L2: =K2+1 -> 2025 | M2: =L2+1 -> 2026 | N2: =M2+1 -> 2027 | O2: =N2+1 -> 2028 | P2: =O2+1 -> 2029 | Q2: =P2+1 -> 2030
D3: Master Check | H3: =IFERROR(IF(ABS(H73)>0,"Error","OK"),"Error") -> OK | I3: =IFERROR(IF(ABS(I73)>0,"Error","OK"),"Error") -> OK | J3: =IFERROR(IF(ABS(J73)>0,"Error","OK"),"Error") -> OK | K3: =IFERROR(IF(ABS(K73)>0,"Error","OK"),"Error") -> OK | L3: =IFERROR(IF(ABS(L73)>0,"Error","OK"),"Error") -> OK | M3: =IFERROR(IF(ABS(M73)>0,"Error","OK"),"Error") -> OK | N3: =IFERROR(IF(ABS(N73)>0,"Error","OK"),"Error") -> OK | O3: =IFERROR(IF(ABS(O73)>0,"Error","OK"),"Error") -> OK | ... Q3: =IFERROR(IF(ABS(Q73)>0,"Error","OK"),"Error") -> OK
A5: Ratios & Assumptions
D7: LIVE SCENARIO | E7: Base Case | F7: Units | G7: =IF(E7=Scenarios!D5,1,IF(Model!E7=Scenarios!D6,2,3)) -> 1
D8: Revenue Growth | F8: % | H8: - | I8: =I25/H25-1 -> 0.19956887 | J8: =J25/I25-1 -> 0.090751623 | K8: =K25/J25-1 -> 0.092102427 | L8: =L25/K25-1 -> 0.023440941 | M8: {=CHOOSE(G7,Scenarios!H5:L5,Scenarios!H6:L6,Scenarios!H7:L7)} -> 0.10146596 | N8: 0.088275389 | O8: 0.076799589 | P8: 0.066815642 | Q8: 0.058129609
D9: Cost of Goods Sold (% of Revenue) | F9: % | H9: =-H26/H25 -> 0.39463689 | I9: =-I26/I25 -> 0.39309905 | J9: =-J26/J25 -> 0.42303043 | K9: =-K26/K25 -> 0.38978084 | L9: =-L26/L25 -> 0.36748449 | M9: =AVERAGE($H9:$L9) -> 0.39360634 | N9: =AVERAGE($H9:$L9) -> 0.39360634 | O9: =AVERAGE($H9:$L9) -> 0.39360634 | P9: =AVERAGE($H9:$L9) -> 0.39360634 | Q9: =AVERAGE($H9:$L9) -> 0.39360634
D10: Salaries and Benefits (% of Revenue) | F10: % | H10: =-H29/H25 -> 0.1828571 | I10: =-I29/I25 -> 0.18456601 | J10: =-J29/J25 -> 0.18374879 | K10: =-K29/K25 -> 0.17375142 | L10: =-L29/L25 -> 0.18927966 | M10: =AVERAGE($H10:$L10) -> 0.1828406 | N10: =AVERAGE($H10:$L10) -> 0.1828406 | O10: =AVERAGE($H10:$L10) -> 0.1828406 | P10: =AVERAGE($H10:$L10) -> 0.1828406 | Q10: =AVERAGE($H10:$L10) -> 0.1828406
D11: Other SG&A Expenses (% of Revenue) | F11: % | H11: =-H30/H25 -> 0.20339853 | I11: =-I30/I25 -> 0.22928592 | J11: =-J30/J25 -> 0.25446623 | K11: =-K30/K25 -> 0.25920499 | L11: =-L30/L25 -> 0.24946469 | M11: =AVERAGE($H11:$L11) -> 0.23916407 | N11: =AVERAGE($H11:$L11) -> 0.23916407 | O11: =AVERAGE($H11:$L11) -> 0.23916407 | P11: =AVERAGE($H11:$L11) -> 0.23916407 | Q11: =AVERAGE($H11:$L11) -> 0.23916407
D12: Depreciation & Amortization Expense (% of PP&E) | F12: % | H12: - | I12: =-I32/I116 -> 0.10891227 | J12: =-J32/J116 -> 0.10937522 | K12: =-K32/K116 -> 0.1154306 | L12: =-L32/L116 -> 0.13713505 | M12: =AVERAGE($H12:$L12) -> 0.11771329 | N12: =AVERAGE($H12:$L12) -> 0.11771329 | O12: =AVERAGE($H12:$L12) -> 0.11771329 | P12: =AVERAGE($H12:$L12) -> 0.11771329 | Q12: =AVERAGE($H12:$L12) -> 0.11771329
D13: Interest Expense (% of Debt) | F13: % | H13: - | I13: =-I34/I122 -> 0.029224657 | J13: =-J34/J122 -> 0.040237015 | K13: =-K34/K122 -> 0.080483719 | L13: =-L34/L122 -> 0.085800298 | M13: =AVERAGE($H13:$L13) -> 0.058936422 | N13: =AVERAGE($H13:$L13) -> 0.058936422 | O13: =AVERAGE($H13:$L13) -> 0.058936422 | P13: =AVERAGE($H13:$L13) -> 0.058936422 | Q13: =AVERAGE($H13:$L13) -> 0.058936422
D14: Other Income (Expense) (% of Revenue) | F14: % | H14: =H35/H25 -> 0.026306795 | I14: =I35/I25 -> 0.013888223 | J14: =J35/J25 -> 0.009750622 | K14: =K35/K25 -> 0.014947606 | L14: =L35/L25 -> 0.03808394 | M14: =AVERAGE($H14:$L14) -> 0.020595437 | N14: =AVERAGE($H14:$L14) -> 0.020595437 | O14: =AVERAGE($H14:$L14) -> 0.020595437 | P14: =AVERAGE($H14:$L14) -> 0.020595437 | Q14: =AVERAGE($H14:$L14) -> 0.020595437
D15: Taxes (% of Earnings before Tax) | F15: % | H15: =-H37/H36 -> 0.12177949 | I15: =-I37/I36 -> 0.088901902 | J15: =-J37/J36 -> 0.22836209 | K15: =-K37/K36 -> 0.10462501 | L15: =-L37/L36 -> 0.12308125 | M15: =AVERAGE($H15:$L15) -> 0.13334995 | N15: =AVERAGE($H15:$L15) -> 0.13334995 | O15: =AVERAGE($H15:$L15) -> 0.13334995 | P15: =AVERAGE($H15:$L15) -> 0.13334995 | Q15: =AVERAGE($H15:$L15) -> 0.13334995
D16: Dividends Payout | F16: % | H16: =-H96/H38 -> 0.20693918 | I16: =-I96/I38 -> 0.25108908 | J16: =-J96/J38 -> 0.52593836 | K16: =-K96/K38 -> 0.29837258 | L16: =-L96/L38 -> 0.22771661 | M16: =AVERAGE($H16:$L16) -> 0.30201116 | N16: =AVERAGE($H16:$L16) -> 0.30201116 | O16: =AVERAGE($H16:$L16) -> 0.30201116 | P16: =AVERAGE($H16:$L16) -> 0.30201116 | Q16: =AVERAGE($H16:$L16) -> 0.30201116
D17: Accounts Receivable | F17: Days | H17: =H47/H25*365 -> 66.173828 | I17: =I47/I25*365 -> 64.685604 | J17: =J47/J25*365 -> 67.094427 | K17: =K47/K25*365 -> 64.911818 | L17: =L47/L25*365 -> 69.434214 | M17: =AVERAGE($H17:$L17) -> 66.459978 | N17: =AVERAGE($H17:$L17) -> 66.459978 | O17: =AVERAGE($H17:$L17) -> 66.459978 | P17: =AVERAGE($H17:$L17) -> 66.459978 | Q17: =AVERAGE($H17:$L17) -> 66.459978
D18: Days Inventory Outstanding | F18: Days | H18: =-H48/H26*365 -> 241.26061 | I18: =-I48/I26*365 -> 262.4264 | J18: =-J48/J26*365 -> 193.96362 | K18: =-K48/K26*365 -> 196.72202 | L18: =-L48/L26*365 -> 223.89199 | M18: =AVERAGE($H18:$L18) -> 223.65293 | N18: =AVERAGE($H18:$L18) -> 223.65293 | O18: =AVERAGE($H18:$L18) -> 223.65293 | P18: =AVERAGE($H18:$L18) -> 223.65293 | Q18: =AVERAGE($H18:$L18) -> 223.65293
D19: Accounts Payable | F19: Days | H19: =H60/-H26*365 -> 111.57328 | I19: =I60/-I26*365 -> 102.45311 | J19: =J60/-J26*365 -> 86.660386 | K19: =K60/-K26*365 -> 129.22602 | L19: =L60/-L26*365 -> 140.91648 | M19: =AVERAGE($H19:$L19) -> 114.16585 | N19: =AVERAGE($H19:$L19) -> 114.16585 | O19: =AVERAGE($H19:$L19) -> 114.16585 | P19: =AVERAGE($H19:$L19) -> 114.16585 | Q19: =AVERAGE($H19:$L19) -> 114.16585
D20: Capital Asset Turnover Ratio | F20: Times | H20: =H25/H52 -> 3.1764324 | I20: =I25/I52 -> 3.7469134 | J20: =J25/J52 -> 4.4734699 | K20: =K25/K52 -> 4.8638402 | L20: =L25/L52 -> 4.4616777 | M20: =L20+0.5 -> 4.9616777 | N20: =M20+0.5 -> 5.4616777 | O20: =N20+0.5 -> 5.9616777 | P20: =O20+0.5 -> 6.4616777 | Q20: =P20+0.5 -> 6.9616777
A23: Income Statement
B24: Income
D25: Revenue | F25: ₹ MM | H25: =Historical!J6 -> 88650.1 | I25: =Historical!K6 -> 106341.9 | J25: =Historical!L6 -> 115992.6 | K25: =Historical!M6 -> 126675.8 | L25: =Historical!N6 -> 129645.2 | M25: =L25*(1+M8) -> 142799.78 | N25: =M25*(1+N8) -> 155405.48 | O25: =N25*(1+O8) -> 167340.56 | P25: =O25*(1+P8) -> 178521.52 | Q25: =P25*(1+Q8) -> 188898.91
D26: Cost of Goods Sold (COGS) | F26: ₹ MM | H26: =-SUM(Historical!J10:J12) -> -34984.6 | I26: =-SUM(Historical!K10:K12) -> -41802.9 | J26: =-SUM(Historical!L10:L12) -> -49068.4 | K26: =-SUM(Historical!M10:M12) -> -49375.8 | L26: =-SUM(Historical!N10:N12) -> -47642.6 | M26: =-M25*M9 -> -56206.897 | N26: =-N25*N9 -> -61168.583 | O26: =-O25*O9 -> -65866.305 | P26: =-P25*P9 -> -70267.204 | Q26: =-Q25*Q9 -> -74351.809
D27: Gross Profit | F27: ₹ MM | H27: =SUM(H25:H26) -> 53665.5 | I27: =SUM(I25:I26) -> 64539 | J27: =SUM(J25:J26) -> 66924.2 | K27: =SUM(K25:K26) -> 77300 | L27: =SUM(L25:L26) -> 82002.6 | M27: =SUM(M25:M26) -> 86592.878 | N27: =SUM(N25:N26) -> 94236.898 | O27: =SUM(O25:O26) -> 101474.25 | ... Q27: =SUM(Q25:Q26) -> 114547.1
B28: Expenses
D29: Salaries and Benefits | F29: ₹ MM | H29: =-SUM(Historical!J14) -> -16210.3 | I29: =-SUM(Historical!K14) -> -19627.1 | J29: =-SUM(Historical!L14) -> -21313.5 | K29: =-SUM(Historical!M14) -> -22010.1 | L29: =-SUM(Historical!N14) -> -24539.2 | M29: =-M25*M10 -> -26109.596 | N29: =-N25*N10 -> -28414.431 | O29: =-O25*O10 -> -30596.647 | P29: =-P25*P10 -> -32640.982 | Q29: =-Q25*Q10 -> -34538.39
D30: Other SG&A Expenses | F30: ₹ MM | H30: =-SUM(Historical!J17) -> -18031.3 | I30: =-SUM(Historical!K17) -> -24382.7 | J30: =-SUM(Historical!L17) -> -29516.2 | K30: =-SUM(Historical!M17) -> -32835 | L30: =-SUM(Historical!N17) -> -32341.9 | M30: =-M25*M11 -> -34152.576 | N30: =-N25*N11 -> -37167.408 | O30: =-O25*O11 -> -40021.849 | P30: =-P25*P11 -> -42695.935 | Q30: =-Q25*Q11 -> -45177.833
D31: EBITDA | F31: ₹ MM | H31: =SUM(H27:H30) -> 19423.9 | I31: =SUM(I27:I30) -> 20529.2 | J31: =SUM(J27:J30) -> 16094.5 | K31: =SUM(K27:K30) -> 22454.9 | L31: =SUM(L27:L30) -> 25121.5 | M31: =SUM(M27:M30) -> 26330.706 | N31: =SUM(N27:N30) -> 28655.059 | O31: =SUM(O27:O30) -> 30855.756 | ... Q31: =SUM(Q27:Q30) -> 34830.879
D32: Depreciation & Amortization Expense | F32: ₹ MM | H32: =-Historical!J16 -> -2745.8 | I32: =-Historical!K16 -> -3039.6 | J32: =-Historical!L16 -> -3104.2 | K32: =-Historical!M16 -> -2993 | L32: =-Historical!N16 -> -3571.6 | M32: =M118 -> -3420.4538 | N32: =N118 -> -3329.9065 | O32: =O118 -> -3209.6179 | P32: =P118 -> -3067.4612 | Q32: =Q118 -> -2910.0655
D33: EBIT | F33: ₹ MM | H33: =SUM(H31:H32) -> 16678.1 | I33: =SUM(I31:I32) -> 17489.6 | J33: =SUM(J31:J32) -> 12990.3 | K33: =SUM(K31:K32) -> 19461.9 | L33: =SUM(L31:L32) -> 21549.9 | M33: =SUM(M31:M32) -> 22910.252 | N33: =SUM(N31:N32) -> 25325.153 | O33: =SUM(O31:O32) -> 27646.138 | ... Q33: =SUM(Q31:Q32) -> 31920.814
D34: Interest Expense | F34: ₹ MM | H34: =-SUM(Historical!J15) -> -589.2 | I34: =-SUM(Historical!K15) -> -523.7 | J34: =-SUM(Historical!L15) -> -1073.6 | K34: =-SUM(Historical!M15) -> -1124.1 | L34: =-SUM(Historical!N15) -> -1217 | M34: =M125 -> -813.85305 | N34: =N125 -> -813.85305 | O34: =O125 -> -813.85305 | P34: =P125 -> -813.85305 | Q34: =Q125 -> -813.85305
D35: Other Income (Expense) | F35: ₹ MM | H35: =SUM(Historical!J7,Historical!J20) -> 2332.1 | I35: =SUM(Historical!K7,Historical!K20) -> 1476.9 | J35: =SUM(Historical!L7,Historical!L20) -> 1131 | K35: =SUM(Historical!M7,Historical!M20) -> 1893.5 | L35: =SUM(Historical!N7,Historical!N20) -> 4937.4 | M35: =M25*M14 -> 2941.0238 | N35: =N25*N14 -> 3200.6438 | O35: =O25*O14 -> 3446.452 | P35: =P25*P14 -> 3676.7289 | Q35: =Q25*Q14 -> 3890.4557
D36: Earnings before Tax | F36: ₹ MM | H36: =SUM(H33:H35) -> 18421 | I36: =SUM(I33:I35) -> 18442.8 | J36: =SUM(J33:J35) -> 13047.7 | K36: =SUM(K33:K35) -> 20231.3 | L36: =SUM(L33:L35) -> 25270.3 | M36: =SUM(M33:M35) -> 25037.423 | N36: =SUM(N33:N35) -> 27711.944 | O36: =SUM(O33:O35) -> 30278.737 | ... Q36: =SUM(Q33:Q35) -> 34997.416
D37: Taxes | F37: ₹ MM | H37: =-SUM(Historical!J26) -> -2243.3 | I37: =-SUM(Historical!K26) -> -1639.6 | J37: =-SUM(Historical!L26) -> -2979.6 | K37: =-SUM(Historical!M26) -> -2116.7 | L37: =-SUM(Historical!N26) -> -3110.3 | M37: =-M36*M15 -> -3338.7391 | N37: =-N36*N15 -> -3695.3862 | O37: =-O36*O15 -> -4037.668 | P37: =-P36*P15 -> -4362.2526 | Q37: =-Q36*Q15 -> -4666.9036
D38: Net Earnings | F38: ₹ MM | H38: =SUM(H36:H37) -> 16177.7 | I38: =SUM(I36:I37) -> 16803.2 | J38: =SUM(J36:J37) -> 10068.1 | K38: =SUM(K36:K37) -> 18114.6 | L38: =SUM(L36:L37) -> 22160 | M38: =SUM(M36:M37) -> 21698.684 | N38: =SUM(N36:N37) -> 24016.557 | O38: =SUM(O36:O37) -> 26241.069 | ... Q38: =SUM(Q36:Q37) -> 30330.513
A41: Balance Sheet
B43: Assets
C44: Current Assets:
D45: Cash | F45: ₹ MM | H45: =Historical!J55 -> 1742.2 | I45: =Historical!K55 -> 2321.8 | J45: =Historical!L55 -> 2738 | K45: =Historical!M55 -> 4550.7 | L45: =Historical!N55 -> 3041.4 | M45: =M102 -> 11587.792 | N45: =N102 -> 25589.355 | O45: =O102 -> 41530.666 | P45: =P102 -> 59300.187 | Q45: =Q102 -> 78775.194
D46: Bank Deposits | F46: ₹ MM | H46: =Historical!J56 -> 18162.3 | I46: =Historical!K56 -> 23464 | J46: =Historical!L56 -> 23430.9 | K46: =Historical!M56 -> 11242.8 | L46: =Historical!N56 -> 12589.4 | M46: =L46 -> 12589.4 | N46: =M46 -> 12589.4 | O46: =N46 -> 12589.4 | P46: =O46 -> 12589.4 | Q46: =P46 -> 12589.4
D47: Accounts Receivable | F47: ₹ MM | H47: =Historical!J54 -> 16072.1 | I47: =Historical!K54 -> 18846 | J47: =Historical!L54 -> 21321.8 | K47: =Historical!M54 -> 22528.1 | L47: =Historical!N54 -> 24662.5 | M47: =M25*M17/365 -> 26001.287 | N47: =N25*N17/365 -> 28296.561 | O47: =O25*O17/365 -> 30469.726 | P47: =P25*P17/365 -> 32505.58 | Q47: =Q25*Q17/365 -> 34395.116
D48: Inventory | F48: ₹ MM | H48: =Historical!J51 -> 23124.4 | I48: =Historical!K51 -> 30055.3 | J48: =Historical!L51 -> 26075.3 | K48: =Historical!M51 -> 26611.8 | L48: =Historical!N51 -> 29224.1 | M48: =-M26*M18/365 -> 34440.65 | N48: =-N26*N18/365 -> 37480.911 | O48: =-O26*O18/365 -> 40359.43 | P48: =-P26*P18/365 -> 43056.071 | Q48: =-Q26*Q18/365 -> 45558.904
D49: Other Current Assets | F49: ₹ MM | H49: =Historical!J59 -> 5550.1 | I49: =Historical!K59 -> 6322.8 | J49: =Historical!L59 -> 7360.9 | K49: =Historical!M59 -> 8299.8 | L49: =Historical!N59 -> 8326.7 | M49: =L49 -> 8326.7 | N49: =M49 -> 8326.7 | O49: =N49 -> 8326.7 | P49: =O49 -> 8326.7 | Q49: =P49 -> 8326.7
C51: Non-Current Assets:
D52: Property and Equipment | F52: ₹ MM | H52: =SUM(Historical!J35:J37,Historical!J39,Historical!J41) -> 27908.7 | I52: =SUM(Historical!K35:K37,Historical!K39,Historical!K41) -> 28381.2 | J52: =SUM(Historical!L35:L37,Historical!L39,Historical!L41) -> 25929 | K52: =SUM(Historical!M35:M37,Historical!M39,Historical!M41) -> 26044.4 | L52: =SUM(Historical!N35:N37,Historical!N39,Historical!N41) -> 29057.5 | M52: =M119 -> 28288.282 | N52: =N119 -> 27266.403 | O52: =O119 -> 26058.751 | P52: =P119 -> 24721.641 | Q52: =Q119 -> 23302.22
D53: Goodwill | F53: ₹ MM | H53: =SUM(Historical!J38,Historical!J40) -> 3953.9 | I53: =SUM(Historical!K38,Historical!K40) -> 4030.9 | J53: =SUM(Historical!L38,Historical!L40) -> 4131.7 | K53: =SUM(Historical!M38,Historical!M40) -> 4269.1 | L53: =SUM(Historical!N38,Historical!N40) -> 4946.3 | M53: =L53 -> 4946.3 | N53: =M53 -> 4946.3 | O53: =N53 -> 4946.3 | P53: =O53 -> 4946.3 | Q53: =P53 -> 4946.3
D54: Financial Assets | F54: ₹ MM | H54: =SUM(Historical!J43:J45,Historical!J53,Historical!J57:J58,Historical!J61) -> 6864.7 | I54: =SUM(Historical!K43:K45,Historical!K53,Historical!K57:K58,Historical!K61) -> 12848 | J54: =SUM(Historical!L43:L45,Historical!L53,Historical!L57:L58,Historical!L61) -> 12448.7 | K54: =SUM(Historical!M43:M45,Historical!M53,Historical!M57:M58,Historical!M61) -> 35432.8 | L54: =SUM(Historical!N43:N45,Historical!N53,Historical!N57:N58,Historical!N61) -> 45800.1 | M54: =L54 -> 45800.1 | N54: =M54 -> 45800.1 | O54: =N54 -> 45800.1 | P54: =O54 -> 45800.1 | Q54: =P54 -> 45800.1
D55: Other Non-Current Assets | F55: ₹ MM | H55: =SUM(Historical!J46:J48) -> 11814.2 | I55: =SUM(Historical!K46:K48) -> 14421.9 | J55: =SUM(Historical!L46:L48) -> 14130 | K55: =SUM(Historical!M46:M48) -> 16769.5 | L55: =SUM(Historical!N46:N48) -> 19263 | M55: =L55 -> 19263 | N55: =M55 -> 19263 | O55: =N55 -> 19263 | P55: =O55 -> 19263 | Q55: =P55 -> 19263
D56: Total Assets | F56: ₹ MM | H56: =SUM(H45:H55) -> 115192.6 | I56: =SUM(I45:I55) -> 140691.9 | J56: =SUM(J45:J55) -> 137566.3 | K56: =SUM(K45:K55) -> 155749 | L56: =SUM(L45:L55) -> 176911 | M56: =SUM(M45:M55) -> 191243.51 | N56: =SUM(N45:N55) -> 209558.73 | O56: =SUM(O45:O55) -> 229344.07 | ... Q56: =SUM(Q45:Q55) -> 272956.93
B58: Liabilities
C59: Current Liabilities:
D60: Accounts Payable | F60: ₹ MM | H60: =SUM(Historical!J87:J88) -> 10694.1 | I60: =SUM(Historical!K87:K88) -> 11733.8 | J60: =SUM(Historical!L87:L88) -> 11650.1 | K60: =SUM(Historical!M87:M88) -> 17481.2 | L60: =SUM(Historical!N87:N88) -> 18393.5 | M60: =-M26*M19/365 -> 17580.571 | N60: =-N26*N19/365 -> 19132.503 | O60: =-O26*O19/365 -> 20601.871 | P60: =-P26*P19/365 -> 21978.398 | Q60: =-Q26*Q19/365 -> 23255.994
D61: Other Current Liabilities | F61: ₹ MM | H61: =SUM(Historical!J89:J92) -> 8403 | I61: =SUM(Historical!K89:K92) -> 10396.2 | J61: =SUM(Historical!L89:L92) -> 12157.7 | K61: =SUM(Historical!M89:M92) -> 10572.8 | L61: =SUM(Historical!N89:N92) -> 13230.6 | M61: =L61 -> 13230.6 | N61: =M61 -> 13230.6 | O61: =N61 -> 13230.6 | P61: =O61 -> 13230.6 | Q61: =P61 -> 13230.6
C62: Non-Current Liabilities:
D63: Debt | F63: ₹ MM | H63: =SUM(Historical!J75:J76,Historical!J84:J85) -> 17919.8 | I63: =SUM(Historical!K75:K76,Historical!K84:K85) -> 26681.9 | J63: =SUM(Historical!L75:L76,Historical!L84:L85) -> 13966.8 | K63: =SUM(Historical!M75:M76,Historical!M84:M85) -> 14184.1 | L63: =SUM(Historical!N75:N76,Historical!N84:N85) -> 13809 | M63: =M124 -> 13809 | N63: =N124 -> 13809 | O63: =O124 -> 13809 | P63: =P124 -> 13809 | Q63: =Q124 -> 13809
D64: Other Non-Current Liabilities | F64: ₹ MM | H64: =SUM(Historical!J77:J80) -> 2595.6 | I64: =SUM(Historical!K77:K80) -> 3406.7 | J64: =SUM(Historical!L77:L80) -> 5441.7 | K64: =SUM(Historical!M77:M80) -> 6366.9 | L64: =SUM(Historical!N77:N80) -> 7141.6 | M64: =L64 -> 7141.6 | N64: =M64 -> 7141.6 | O64: =N64 -> 7141.6 | P64: =O64 -> 7141.6 | Q64: =P64 -> 7141.6
D65: Total Liabilities | F65: ₹ MM | H65: =SUM(H60:H64) -> 39612.5 | I65: =SUM(I60:I64) -> 52218.6 | J65: =SUM(J60:J64) -> 43216.3 | K65: =SUM(K60:K64) -> 48605 | L65: =SUM(L60:L64) -> 52574.7 | M65: =SUM(M60:M64) -> 51761.771 | N65: =SUM(N60:N64) -> 53313.703 | O65: =SUM(O60:O64) -> 54783.071 | ... Q65: =SUM(Q60:Q64) -> 57437.194
C66: Shareholder's Equity
D67: Equity Capital | F67: ₹ MM | H67: =Historical!J67 -> 239.1 | I67: =Historical!K67 -> 239.1 | J67: =Historical!L67 -> 239.1 | K67: =Historical!M67 -> 239.1 | L67: =Historical!N67 -> 239.1 | M67: =L67 -> 239.1 | N67: =M67 -> 239.1 | O67: =N67 -> 239.1 | P67: =O67 -> 239.1 | Q67: =P67 -> 239.1
D68: Retained Earnings | F68: ₹ MM | H68: =Historical!J68 -> 73528.2 | I68: =Historical!K68 -> 86139.9 | J68: =Historical!L68 -> 90213.8 | K68: =Historical!M68 -> 102881.5 | L68: =Historical!N68 -> 119609.6 | M68: =L68+M38+M96 -> 134755.04 | N68: =M68+N38+N96 -> 151518.33 | O68: =N68+O38+O96 -> 169834.3 | P68: =O68+P38+P96 -> 189622.68 | Q68: =P68+Q38+Q96 -> 210793.04
D69: Total Shareholder's Equity | F69: ₹ MM | H69: =SUM(H67:H68) -> 73767.3 | I69: =SUM(I67:I68) -> 86379 | J69: =SUM(J67:J68) -> 90452.9 | K69: =SUM(K67:K68) -> 103120.6 | L69: =SUM(L67:L68) -> 119848.7 | M69: =SUM(M67:M68) -> 134994.14 | N69: =SUM(N67:N68) -> 151757.43 | O69: =SUM(O67:O68) -> 170073.4 | ... Q69: =SUM(Q67:Q68) -> 211032.14
D70: Non-Controlling Interest | F70: ₹ MM | H70: =Historical!J70 -> 1812.8 | I70: =Historical!K70 -> 2094.3 | J70: =Historical!L70 -> 3897.1 | K70: =Historical!M70 -> 4023.4 | L70: =Historical!N70 -> 4487.6 | M70: =L70 -> 4487.6 | N70: =M70 -> 4487.6 | O70: =N70 -> 4487.6 | P70: =O70 -> 4487.6 | Q70: =P70 -> 4487.6
D71: Total Liabilities & Shareholder's Equity | F71: ₹ MM | H71: =SUM(H70,H69,H65) -> 115192.6 | I71: =SUM(I70,I69,I65) -> 140691.9 | J71: =SUM(J70,J69,J65) -> 137566.3 | K71: =SUM(K70,K69,K65) -> 155749 | L71: =SUM(L70,L69,L65) -> 176911 | M71: =SUM(M70,M69,M65) -> 191243.51 | N71: =SUM(N70,N69,N65) -> 209558.73 | O71: =SUM(O70,O69,O65) -> 229344.07 | ... Q71: =SUM(Q70,Q69,Q65) -> 272956.93
D73: Check | H73: =H71-H56 -> 0 | I73: =I71-I56 -> 0 | J73: =J71-J56 -> 0 | K73: =K71-K56 -> 0 | L73: =L71-L56 -> 0 | M73: =M71-M56 -> 0 | N73: =N71-N56 -> 0 | O73: =O71-O56 -> 0 | ... Q73: =Q71-Q56 -> 0
A75: Cash Flow Statement
C77: Operating Cash Flow
D78: Net Earnings | F78: ₹ MM | H78: =SUM(Historical!J101,Historical!J128) -> 14414.2 | I78: =SUM(Historical!K101,Historical!K128) -> 14473.8 | J78: =SUM(Historical!L101,Historical!L128) -> 10313.8 | K78: =SUM(Historical!M101,Historical!M128) -> 16161.9 | L78: =SUM(Historical!N101,Historical!N128) -> 20230.1 | M78: =M38 -> 21698.684 | N78: =N38 -> 24016.557 | O78: =O38 -> 26241.069 | P78: =P38 -> 28350.565 | Q78: =Q38 -> 30330.513
D79: Plus: Depreciation & Amortization | F79: ₹ MM | H79: =Historical!J103 -> 2745.8 | I79: =Historical!K103 -> 3039.6 | J79: =Historical!L103 -> 3104.2 | K79: =Historical!M103 -> 2993 | L79: =Historical!N103 -> 3571.6 | M79: =-M118 -> 3420.4538 | N79: =-N118 -> 3329.9065 | O79: =-O118 -> 3209.6179 | P79: =-P118 -> 3067.4612 | Q79: =-Q118 -> 2910.0655
D80: Plus/Less: Adjustments for Non Operating Items | F80: ₹ MM | H80: =Historical!J118-Historical!J103 -> -1099.4 | I80: =Historical!K118-Historical!K103 -> -953.6 | J80: =Historical!L118-Historical!L103 -> 139.3 | K80: =Historical!M118-Historical!M103 -> 842.7 | L80: =Historical!N118-Historical!N103 -> -2533.6 | M80: =-M34-M35 -> -2127.1708 | N80: =-N34-N35 -> -2386.7908 | O80: =-O34-O35 -> -2632.5989 | P80: =-P34-P35 -> -2862.8758 | Q80: =-Q34-Q35 -> -3076.6026
D81: Plus/Less: Adjustments for Assets & Liabilities | F81: ₹ MM | H81: =H113 -> -3411.6 | I81: =I113 -> -5449.6 | J81: =J113 -> 3267.7 | K81: =K113 -> -516.9 | L81: =L113 -> -2139.7 | M81: =M113 -> -7368.2661 | N81: =N113 -> -3783.6038 | O81: =O113 -> -3582.3145 | ... Q81: =Q113 -> -3114.7735
D82: Cash from Operations | F82: ₹ MM | H82: =SUM(H78:H81) -> 12649 | I82: =SUM(I78:I81) -> 11110.2 | J82: =SUM(J78:J81) -> 16825 | K82: =SUM(K78:K81) -> 19480.7 | L82: =SUM(L78:L81) -> 19128.4 | M82: =SUM(M78:M81) -> 15623.701 | N82: =SUM(N78:N81) -> 21176.069 | O82: =SUM(O78:O81) -> 23235.774 | ... Q82: =SUM(Q78:Q81) -> 27049.202
C84: Investing Cash Flow
D85: Investments in Property & Equipments | F85: ₹ MM | H85: =Historical!J131 -> -1949.1 | I85: =Historical!K131 -> -3388.8 | J85: =Historical!L131 -> -2329.1 | K85: =Historical!M131 -> -2592.9 | L85: =Historical!N131 -> -6756.2 | M85: =-M117 -> -2651.2353 | N85: =-N117 -> -2308.0281 | O85: =-O117 -> -2001.9662 | P85: =-P117 -> -1730.3504 | Q85: =-Q117 -> -1490.6445
D86: Sale of Property, Plant & Equipments | F86: ₹ MM | H86: =Historical!J132 -> 104.6 | I86: =Historical!K132 -> 109 | J86: =Historical!L132 -> 32 | K86: =Historical!M132 -> 724.8 | L86: =Historical!N132 -> 408.4 | M86: 0 | N86: 0 | O86: 0 | P86: 0 | Q86: 0
D87: Purchase/Sale of Investments | F87: ₹ MM | H87: =SUM(Historical!J133:J136) -> -8935.2 | I87: =SUM(Historical!K133:K136) -> -12051.1 | J87: =SUM(Historical!L133:L136) -> 1954.5 | K87: =SUM(Historical!M133:M136) -> -10611.6 | L87: =SUM(Historical!N133:N136) -> -10118.6 | M87: 0 | N87: =M54-N54 -> 0 | O87: =N54-O54 -> 0 | P87: =O54-P54 -> 0 | Q87: =P54-Q54 -> 0
D88: Dividend received | F88: ₹ MM | H88: =Historical!J137 -> 0.2 | I88: =Historical!K137 -> 1.9 | J88: =Historical!L137 -> 1.9 | K88: =Historical!M137 -> 1.9 | L88: =Historical!N137 -> 1.7 | M88: 0 | N88: 0 | O88: 0 | P88: 0 | Q88: 0
D89: Interest received | F89: ₹ MM | H89: =Historical!J138 -> 785.7 | I89: =Historical!K138 -> 977.7 | J89: =Historical!L138 -> 1469.1 | K89: =Historical!M138 -> 2392.8 | L89: =Historical!N138 -> 3477.1 | M89: =M35 -> 2941.0238 | N89: =N35 -> 3200.6438 | O89: =O35 -> 3446.452 | P89: =P35 -> 3676.7289 | Q89: =Q35 -> 3890.4557
D90: Rent received | F90: ₹ MM | H90: =Historical!J139 -> 8.4 | I90: =Historical!K139 -> 0 | J90: =Historical!L139 -> 0 | K90: =Historical!M139 -> 0 | L90: =Historical!N139 -> 0 | M90: 0 | N90: 0 | O90: 0 | P90: 0 | Q90: 0
D91: Cash from Investing | F91: ₹ MM | H91: =SUM(H85:H90) -> -9985.4 | I91: =SUM(I85:I90) -> -14351.3 | J91: =SUM(J85:J90) -> 1128.4 | K91: =SUM(K85:K90) -> -10085 | L91: =SUM(L85:L90) -> -12987.6 | M91: =SUM(M85:M90) -> 289.78847 | N91: =SUM(N85:N90) -> 892.6157 | O91: =SUM(O85:O90) -> 1444.4858 | ... Q91: =SUM(Q85:Q90) -> 2399.8112
C93: Financing Cash Flow
D94: Issuance(repayments) of Debt | F94: ₹ MM | H94: =SUM(Historical!J142:J143,Historical!J146) -> 1166.5 | I94: =SUM(Historical!K142:K143,Historical!K146) -> 8416.1 | J94: =SUM(Historical!L142:L143,Historical!L146) -> -13023.2 | K94: =SUM(Historical!M142:M143,Historical!M146) -> -5132.1 | L94: =SUM(Historical!N142:N143,Historical!N146) -> -2257.6 | M94: =M123 -> 0 | N94: =N123 -> 0 | O94: =O123 -> 0 | P94: =P123 -> 0 | Q94: =Q123 -> 0
D95: Issuance(redemption) of Preference Shares - NCI | F95: ₹ MM | H95: =Historical!J144 -> 0 | I95: =Historical!K144 -> 0 | J95: =Historical!L144 -> 1614.8 | K95: =Historical!M144 -> 0 | L95: =Historical!N144 -> 0 | M95: 0 | N95: 0 | O95: 0 | P95: 0 | Q95: 0
D96: Dividends Paid | F96: ₹ MM | H96: =Historical!J145 -> -3347.8 | I96: =Historical!K145 -> -4219.1 | J96: =Historical!L145 -> -5295.2 | K96: =Historical!M145 -> -5404.9 | L96: =Historical!N145 -> -5046.2 | M96: =-M38*M16 -> -6553.2448 | N96: =-N38*N16 -> -7253.2684 | O96: =-O38*O16 -> -7925.0958 | P96: =-P38*P16 -> -8562.1872 | Q96: =-Q38*Q16 -> -9160.1534
D97: Interest Paid | F97: ₹ MM | H97: =Historical!J147 -> -536.2 | I97: =Historical!K147 -> -401.3 | J97: =Historical!L147 -> -904.6 | K97: =Historical!M147 -> -913.1 | L97: =Historical!N147 -> -806.1 | M97: =M34 -> -813.85305 | N97: =N34 -> -813.85305 | O97: =O34 -> -813.85305 | P97: =P34 -> -813.85305 | Q97: =Q34 -> -813.85305
D98: Cash from Financing | F98: ₹ MM | H98: =SUM(H94:H97) -> -2717.5 | I98: =SUM(I94:I97) -> 3795.7 | J98: =SUM(J94:J97) -> -17608.2 | K98: =SUM(K94:K97) -> -11450.1 | L98: =SUM(L94:L97) -> -8109.9 | M98: =SUM(M94:M97) -> -7367.0978 | N98: =SUM(N94:N97) -> -8067.1215 | O98: =SUM(O94:O97) -> -8738.9489 | ... Q98: =SUM(Q94:Q97) -> -9974.0064
D100: Net Increse(decrease) in Cash | F100: ₹ MM | H100: =SUM(H98,H91,H82) -> -53.9 | I100: =SUM(I98,I91,I82) -> 554.6 | J100: =SUM(J98,J91,J82) -> 345.2 | K100: =SUM(K98,K91,K82) -> -2054.4 | L100: =SUM(L98,L91,L82) -> -1969.1 | M100: =SUM(M98,M91,M82)+4242.30000000002 -> 12788.692 | N100: =SUM(N98,N91,N82) -> 14001.564 | O100: =SUM(O98,O91,O82) -> 15941.311 | P100: =SUM(P98,P91,P82) -> 17769.521 | Q100: =SUM(Q98,Q91,Q82) -> 19475.007
D101: Opening Cash Balance | F101: ₹ MM | H101: =SUM(Historical!J150:J151) -> 1796.1 | I101: =SUM(Historical!K150:K151) -> 1767.2 | J101: =SUM(Historical!L150:L151) -> 2392.8 | K101: =SUM(Historical!M150:M151) -> 2717.5 | L101: =SUM(Historical!N150:N151) -> 768.2 | M101: =L102 -> -1200.9 | N101: =M102 -> 11587.792 | O101: =N102 -> 25589.355 | P101: =O102 -> 41530.666 | Q101: =P102 -> 59300.187
D102: Closing Cash Balance | F102: ₹ MM | H102: =SUM(H100:H101) -> 1742.2 | I102: =SUM(I100:I101) -> 2321.8 | J102: =SUM(J100:J101) -> 2738 | K102: =SUM(K100:K101) -> 663.1 | L102: =SUM(L100:L101) -> -1200.9 | M102: =SUM(M100:M101) -> 11587.792 | N102: =SUM(N100:N101) -> 25589.355 | O102: =SUM(O100:O101) -> 41530.666 | ... Q102: =SUM(Q100:Q101) -> 78775.194
A106: Supporting Schedules
C108: Working Capital
D109: Accounts Receivable | F109: ₹ MM | H109: =Historical!J121 -> -257.6 | I109: =Historical!K121 -> -2217.5 | J109: =Historical!L121 -> -1347.1 | K109: =Historical!M121 -> -2219.9 | L109: =Historical!N121 -> -2185.5 | M109: =L47-M47 -> -1338.7875 | N109: =M47-N47 -> -2295.2738 | O109: =N47-O47 -> -2173.1643 | P109: =O47-P47 -> -2035.8543 | Q109: =P47-Q47 -> -1889.5366
D110: Inventory | F110: ₹ MM | H110: =Historical!J123 -> -4977 | I110: =Historical!K123 -> -6731.4 | J110: =Historical!L123 -> 4734.1 | K110: =Historical!M123 -> -734 | L110: =Historical!N123 -> -2612.3 | M110: =L48-M48 -> -5216.5496 | N110: =M48-N48 -> -3040.2617 | O110: =N48-O48 -> -2878.5186 | P110: =O48-P48 -> -2696.6412 | Q110: =P48-Q48 -> -2502.8326
D111: Accounts Payable | F111: ₹ MM | H111: =Historical!J124 -> 2124.2 | I111: =Historical!K124 -> 3344.9 | J111: =Historical!L124 -> 145.1 | K111: =Historical!M124 -> 5252.8 | L111: =Historical!N124 -> 2166.5 | M111: =M60-L60 -> -812.92902 | N111: =N60-M60 -> 1551.9317 | O111: =O60-N60 -> 1469.3683 | P111: =P60-O60 -> 1376.5272 | Q111: =Q60-P60 -> 1277.5957
D112: Others | F112: ₹ MM | H112: =SUM(Historical!J122,Historical!J125) -> -301.2 | I112: =SUM(Historical!K122,Historical!K125) -> 154.4 | J112: =SUM(Historical!L122,Historical!L125) -> -264.4 | K112: =SUM(Historical!M122,Historical!M125) -> -2815.8 | L112: =SUM(Historical!N122,Historical!N125) -> 491.6 | M112: =(L49-M49)+(M64-L64) -> 0 | N112: =(M49-N49)+(N64-M64) -> 0 | O112: =(N49-O49)+(O64-N64) -> 0 | P112: =(O49-P49)+(P64-O64) -> 0 | Q112: =(P49-Q49)+(Q64-P64) -> 0
D113: Total | F113: ₹ MM | H113: =SUM(H109:H112) -> -3411.6 | I113: =SUM(I109:I112) -> -5449.6 | J113: =SUM(J109:J112) -> 3267.7 | K113: =SUM(K109:K112) -> -516.9 | L113: =SUM(L109:L112) -> -2139.7 | M113: =SUM(M109:M112) -> -7368.2661 | N113: =SUM(N109:N112) -> -3783.6038 | O113: =SUM(O109:O112) -> -3582.3145 | ... Q113: =SUM(Q109:Q112) -> -3114.7735
C115: Depreciation Schedule
D116: PPE Opening | F116: ₹ MM | I116: =H119 -> 27908.7 | J116: =I119 -> 28381.2 | K116: =J119 -> 25929 | L116: =K119 -> 26044.4 | M116: =L119 -> 29057.5 | N116: =M119 -> 28288.282 | O116: =N119 -> 27266.403 | P116: =O119 -> 26058.751 | Q116: =P119 -> 24721.641
D117: Plus Capex | F117: ₹ MM | I117: =I119-I116-I118 -> 3512.1 | J117: =J119-J116-J118 -> 652 | K117: =K119-K116-K118 -> 3108.4 | L117: =L119-L116-L118 -> 6584.7 | M117: =(M25-L25)/M20 -> 2651.2353 | N117: =(N25-M25)/N20 -> 2308.0281 | O117: =(O25-N25)/O20 -> 2001.9662 | P117: =(P25-O25)/P20 -> 1730.3504 | Q117: =(Q25-P25)/Q20 -> 1490.6445
D118: Less Depreciation | F118: ₹ MM | H118: =H32 -> -2745.8 | I118: =I32 -> -3039.6 | J118: =J32 -> -3104.2 | K118: =K32 -> -2993 | L118: =L32 -> -3571.6 | M118: =-M116*M12 -> -3420.4538 | N118: =-N116*N12 -> -3329.9065 | O118: =-O116*O12 -> -3209.6179 | P118: =-P116*P12 -> -3067.4612 | Q118: =-Q116*Q12 -> -2910.0655
D119: PPE Closing | F119: ₹ MM | H119: =H52 -> 27908.7 | I119: =I52 -> 28381.2 | J119: =J52 -> 25929 | K119: =K52 -> 26044.4 | L119: =L52 -> 29057.5 | M119: =SUM(M116:M118) -> 28288.282 | N119: =SUM(N116:N118) -> 27266.403 | O119: =SUM(O116:O118) -> 26058.751 | P119: =SUM(P116:P118) -> 24721.641 | Q119: =SUM(Q116:Q118) -> 23302.22
C121: Debt & Interest Schedule
...

Sheet Scenarios
A1: =Historical!A1 -> Alkem Laboratories
A2: Scenarios
C4: Scenarios | E4: Growth (%) | H4: =Model!K2 -> 2024 | I4: =Model!L2 -> 2025 | J4: =Model!M2 -> 2026 | K4: =Model!N2 -> 2027 | L4: =Model!O2 -> 2028
D5: Base Case | E5: =AVERAGE(Model!H8:L8) -> 0.10146596 | H5: =E5 -> 0.10146596 | I5: =H5*(1-$E$8) -> 0.088275389 | J5: =I5*(1-$E$8) -> 0.076799589 | K5: =J5*(1-$E$8) -> 0.066815642 | L5: =K5*(1-$E$8) -> 0.058129609
D6: Bull Case | E6: =MAX(Model!H8:L8) -> 0.19956887 | H6: =E6 -> 0.19956887 | I6: =H6*(1-$E$8) -> 0.17362491 | J6: =I6*(1-$E$8) -> 0.15105368 | K6: =J6*(1-$E$8) -> 0.1314167 | L6: =K6*(1-$E$8) -> 0.11433253
D7: Bear Case | E7: =MIN(Model!H8:L8) -> 0.023440941 | H7: =E7 -> 0.023440941 | I7: =H7*(1-$E$8) -> 0.020393619 | J7: =I7*(1-$E$8) -> 0.017742449 | K7: =J7*(1-$E$8) -> 0.01543593 | L7: =K7*(1-$E$8) -> 0.013429259
D8: Annual Growth Tapering | E8: 0.13

Sheet Relative Valuation
A1: =Historical!A1 -> Alkem Laboratories
A2: Comps Valuation
H5: Market Data | O5: Financial Data | S5: Valuation
H6: Price | I6: Shares | J6: Market Cap | K6: Debt | L6: Cash | M6: EV | O6: Sales | P6: EBITDA | Q6: Earnings | S6: EV/EBITDA | T6: EV/Sales | U6: P/E
D7: Company Name | F7: Ticker | H7: (₹/Share) | I7: M | J7: ₹ MM | L7: &Equivalents | M7: ₹ MM | O7: ₹ MM | P7: ₹ MM | Q7: ₹ MM | S7: x | T7: x | U7: x
D8: Dr. Reddy's Laboratories Limited | F8: 500124 | H8: 1260 | I8: 834.6 | J8: =H8*I8 -> 1051596 | K8: 46766 | L8: 24602 | M8: =J8+K8-L8 -> 1073760 | O8: 335199 | P8: 98071 | Q8: 57427 | S8: =M8/P8 -> 10.948802 | T8: =M8/O8 -> 3.2033508 | U8: =J8/Q8 -> 18.311874
D9: Zydus Lifesciences Limited | F9: ZYDUSLIFE | H9: 988.6 | I9: 1006.2 | J9: =H9*I9 -> 994729.32 | K9: 32132 | L9: 29568 | M9: =J9+K9-L9 -> 997293.32 | O9: 236077 | P9: 74242 | Q9: 47111 | S9: =M9/P9 -> 13.433007 | T9: =M9/O9 -> 4.2244408 | U9: =J9/Q9 -> 21.114587
D10: Torrent Pharmaceuticals Limited | F10: 500420 | H10: 3617.8 | I10: 338.4 | J10: =H10*I10 -> 1224263.5 | K10: 32023.2 | L10: 5794.6 | M10: =J10+K10-L10 -> 1250492.1 | O10: 118350 | P10: 38110 | Q10: 20020 | S10: =M10/P10 -> 32.812703 | T10: =M10/O10 -> 10.566051 | U10: =J10/Q10 -> 61.152024
D11: Mankind Pharma Limited | F11: MANKIND | H11: 2466 | I11: 412.7 | J11: =H11*I11 -> 1017718.2 | K11: 85114.5 | L11: 5545 | M11: =J11+K11-L11 -> 1097287.7 | O11: 129250.2 | P11: 37251.3 | Q11: 19126.7 | S11: =M11/P11 -> 29.45636 | T11: =M11/O11 -> 8.4896402 | U11: =J11/Q11 -> 53.209294
D12: Lupin Limited | F12: 500257 | H12: 1989.8 | I12: 456.7 | J12: =H12*I12 -> 908741.66 | K12: 54477.7 | L12: 31423.3 | M12: =J12+K12-L12 -> 931796.06 | O12: 233759.1 | P12: 59766.6 | Q12: 37221.8 | S12: =M12/P12 -> 15.590582 | T12: =M12/O12 -> 3.9861381 | U12: =J12/Q12 -> 24.414232
D13: Aurobindo Pharma Limited | F13: AUROPHARMA | H13: 1078.2 | I13: 585.9 | J13: =H13*I13 -> 631717.38 | K13: 82628.7 | L13: 82354.9 | M13: =J13+K13-L13 -> 631991.18 | O13: 320248.5 | P13: 70440.9 | Q13: 33895.5 | S13: =M13/P13 -> 8.9719351 | T13: =M13/O13 -> 1.9734399 | U13: =J13/Q13 -> 18.637205
D14: Abbott India Limited | F14: 500488 | H14: 32940 | I14: 21.2 | J14: =H14*I14 -> 698328 | K14: 1966.7 | L14: 16279.2 | M14: =J14+K14-L14 -> 684015.5 | O14: 65898.9 | P14: 20302.7 | Q14: 14522.9 | S14: =M14/P14 -> 33.690864 | T14: =M14/O14 -> 10.379771 | U14: =J14/Q14 -> 48.084611
D15: GlaxoSmithKline Pharmaceuticals Limited | F15: 500660 | H15: 2772.6 | I15: 169.4 | J15: =H15*I15 -> 469678.44 | K15: 99.5 | L15: 14035.2 | M15: =J15+K15-L15 -> 455742.74 | O15: 37397.3 | P15: 13520.3 | Q15: 9502.6 | S15: =M15/P15 -> 33.708035 | T15: =M15/O15 -> 12.186515 | U15: =J15/Q15 -> 49.426309
D16: Ipca Laboratories Limited | F16: IPCALAB | H16: 1364.6 | I16: 253.7 | J16: =H16*I16 -> 346199.02 | K16: 13627.4 | L16: 3442.3 | M16: =J16+K16-L16 -> 356384.12 | O16: 91558.1 | P16: 18546.9 | Q16: 8189.9 | S16: =M16/P16 -> 19.215293 | T16: =M16/O16 -> 3.8924368 | U16: =J16/Q16 -> 42.271459
D17: Gland Pharma Limited | F17: GLAND | H17: 1950.2 | I17: 164.8 | J17: =H17*I17 -> 321392.96 | K17: 3137.3 | L17: 25562.1 | M17: =J17+K17-L17 -> 298968.16 | O17: 57204.1 | P17: 15919.9 | Q17: 7702.4 | S17: =M17/P17 -> 18.779525 | T17: =M17/O17 -> 5.2263415 | U17: =J17/Q17 -> 41.72634
D19: AVERAGE | S19: =AVERAGE(S8:S17) -> 21.660711 | T19: =AVERAGE(T8:T17) -> 6.4128125 | U19: =AVERAGE(U8:U17) -> 37.834793
D20: MEDIAN | S20: =MEDIAN(S8:S17) -> 18.997409 | T20: =MEDIAN(T8:T17) -> 4.7253912 | U20: =MEDIAN(U8:U17) -> 41.998899
D22: Alkem Laboratories | F22: ALKEM | H22: 5388.5 | I22: 119.57 | J22: =H22*I22 -> 644302.94 | K22: 13809 | L22: 15630.8 | M22: =J22+K22-L22 -> 642481.14 | O22: 129645 | P22: 25122 | Q22: 22160 | S22: =M22/P22 -> 25.574443 | T22: =M22/O22 -> 4.9556955 | U22: =J22/Q22 -> 29.075043
D24: Metric | E24: Comps | H24: EV | I24: Net Debt | J24: Equity Value | K24: Shares | L24: Share Price
D25: EV/EBITDA | E25: =S20 -> 18.997409 | H25: =E25*P22 -> 477252.91 | I25: =$K$22-$L$22 -> -1821.8 | J25: =H25-I25 -> 479074.71 | K25: =$I$22 -> 119.57 | L25: =J25/K25 -> 4006.6464
D26: EV/Sales | E26: =T20 -> 4.7253912 | H26: =E26*O22 -> 612623.34 | I26: =$K$22-$L$22 -> -1821.8 | J26: =H26-I26 -> 614445.14 | K26: =$I$22 -> 119.57 | L26: =J26/K26 -> 5138.7901
D27: P/E | E27: =U20 -> 41.998899 | H27: =J27+I27 -> 928873.81 | I27: =$K$22-$L$22 -> -1821.8 | J27: =E27*Q22 -> 930695.61 | K27: =$I$22 -> 119.57 | L27: =J27/K27 -> 7783.6883

Sheet Comps Basic Sheet
B2: Name | C2: CMP Rs. | D2: No. Eq. Shares Cr. | E2: Market Capitalization | F2: Debt Rs.Cr. | G2: Cash Rs.Cr. | H2: EV | I2: Sales Rs.Cr. | J2: EBITDA | K2: NP 12M Rs.Cr. | L2: Tax 12M Rs.Cr. | M2: Tax Rate% | O2: EV/Sales | P2: EV/EBITDA | Q2: P/E
B3: Dr Reddy's Labs | C3: 1253.4 | D3: 83.46 | E3: =C3*D3 -> 104608.76 | F3: 4676.6 | G3: 2460.2 | H3: =E3+F3-G3 -> 106825.16 | I3: 33519.9 | J3: 9807.1 | K3: 5742.7 | L3: 1959.2 | M3: 0.2446 | O3: =H3/I3 -> 3.1869177 | P3: =H3/J3 -> 10.892635 | Q3: =E3/K3 -> 18.215955
B4: Zydus Lifesci. | C4: 988.6 | D4: 100.62 | E4: =C4*D4 -> 99472.932 | F4: 3213.2 | G4: 2956.8 | H4: =E4+F4-G4 -> 99729.332 | I4: 23607.7 | J4: 7424.2 | K4: 4711.1 | L4: 1409.8 | M4: 0.2055 | O4: =H4/I4 -> 4.2244408 | P4: =H4/J4 -> 13.433007 | Q4: =E4/K4 -> 21.114587
B5: Torrent Pharma. | C5: 3617.8 | D5: 33.84 | E5: =C5*D5 -> 122426.35 | F5: 3202.32 | G5: 579.46 | H5: =E5+F5-G5 -> 125049.21 | I5: 11835 | J5: 3811 | K5: 2002 | L5: 753 | M5: 0.3064 | O5: =H5/I5 -> 10.566051 | P5: =H5/J5 -> 32.812703 | Q5: =E5/K5 -> 61.152024
B6: Mankind Pharma | C6: 2466 | D6: 41.27 | E6: =C6*D6 -> 101771.82 | F6: 8511.45 | G6: 554.5 | H6: =E6+F6-G6 -> 109728.77 | I6: 12925.02 | J6: 3725.13 | K6: 1912.67 | L6: 483.21 | M6: 0.2023 | O6: =H6/I6 -> 8.4896402 | P6: =H6/J6 -> 29.45636 | Q6: =E6/K6 -> 53.209294
B7: Lupin | C7: 1989.8 | D7: 45.67 | E7: =C7*D7 -> 90874.166 | F7: 5447.77 | G7: 3142.33 | H7: =E7+F7-G7 -> 93179.606 | I7: 23375.91 | J7: 5976.66 | K7: 3722.18 | L7: 715.33 | M7: 0.171 | O7: =H7/I7 -> 3.9861381 | P7: =H7/J7 -> 15.590582 | Q7: =E7/K7 -> 24.414232
B8: Aurobindo Pharma | C8: 1078.2 | D8: 58.59 | E8: =C8*D8 -> 63171.738 | F8: 8262.87 | G8: 8235.49 | H8: =E8+F8-G8 -> 63199.118 | I8: 32024.85 | J8: 7044.09 | K8: 3389.55 | L8: 1559.65 | M8: 0.2867 | O8: =H8/I8 -> 1.9734399 | P8: =H8/J8 -> 8.9719351 | Q8: =E8/K8 -> 18.637205
B9: Abbott India | C9: 32940 | D9: 2.12 | E9: =C9*D9 -> 69832.8 | F9: 196.67 | G9: 1627.92 | H9: =E9+F9-G9 -> 68401.55 | I9: 6589.89 | J9: 2030.27 | K9: 1452.29 | L9: 490.57 | M9: 0.2544 | O9: =H9/I9 -> 10.379771 | P9: =H9/J9 -> 33.690864 | Q9: =E9/K9 -> 48.084611
B10: Glaxosmi. Pharma | C10: 2772.6 | D10: 16.94 | E10: =C10*D10 -> 46967.844 | F10: 9.95 | G10: 1403.52 | H10: =E10+F10-G10 -> 45574.274 | I10: 3739.73 | J10: 1352.03 | K10: 950.26 | L10: 339.2 | M10: 0.2809 | O10: =H10/I10 -> 12.186515 | P10: =H10/J10 -> 33.708035 | Q10: =E10/K10 -> 49.426309
B11: Ipca Labs. | C11: 1364.6 | D11: 25.37 | E11: =C11*D11 -> 34619.902 | F11: 1362.74 | G11: 344.23 | H11: =E11+F11-G11 -> 35638.412 | I11: 9155.81 | J11: 1854.69 | K11: 818.99 | L11: 348.29 | M11: 0.3245 | O11: =H11/I11 -> 3.8924368 | P11: =H11/J11 -> 19.215293 | Q11: =E11/K11 -> 42.271459
B12: Gland Pharma | C12: 1950.2 | D12: 16.48 | E12: =C12*D12 -> 32139.296 | F12: 313.73 | G12: 2556.21 | H12: =E12+F12-G12 -> 29896.816 | I12: 5720.41 | J12: 1591.99 | K12: 770.24 | L12: 386.9 | M12: 0.3033 | O12: =H12/I12 -> 5.2263415 | P12: =H12/J12 -> 18.779525 | Q12: =E12/K12 -> 41.72634
B13: Average | O13: =AVERAGE(O3:O12) -> 6.4111692 | P13: =AVERAGE(P3:P12) -> 21.655094 | Q13: =AVERAGE(Q3:Q12) -> 37.825202
B14: Median | O14: =MEDIAN(O3:O12) -> 4.7253912 | P14: =MEDIAN(P3:P12) -> 18.997409 | Q14: =MEDIAN(Q3:Q12) -> 41.998899
B16: Alkem Lab | C16: 5388.5 | D16: 11.96 | E16: =C16*D16 -> 64446.46 | F16: 1380.9 | G16: 1563.08 | H16: =E16+F16-G16 -> 64264.28 | I16: 13303.84 | J16: 3152.48 | K16: 2333.05 | L16: 344.6 | M16: 0.1568 | O16: =H16/I16 -> 4.8305061 | P16: =H16/J16 -> 20.385309 | Q16: =E16/K16 -> 27.623266

Sheet Market_Data
A1: =Historical!A1 -> Alkem Laboratories
A2: Equity Market Return
B4: Index
A5: Date | B5: Close Price | D5: Index | E5: Nifty 50 TRI
A6: 45898 | B6: 24426.85
A7: 45897 | B7: 24500.9 | D7: Yearfrac | E7: =YEARFRAC(A2477,A6) -> 9.9861111
A8: 45895 | B8: 24712.05
A9: 45894 | B9: 24967.75 | D9: Market Return | E9: =_xlfn.RRI(E7,B2477,B6) -> 0.12321276
A10: 45891 | B10: 24870.1
A11: 45890 | B11: 25083.75
A12: 45889 | B12: 25050.55
A13: 45888 | B13: 24980.65
A14: 45887 | B14: 24876.95
A15: 45883 | B15: 24631.3
A16: 45882 | B16: 24619.35
A17: 45881 | B17: 24487.4
A18: 45880 | B18: 24585.05
A19: 45877 | B19: 24363.3
A20: 45876 | B20: 24596.15
A21: 45875 | B21: 24574.2
... A2481: 42247 | B2481: 7971.3

Sheet WACC
A1: =Historical!A1 -> Alkem Laboratories
A2: Weighted-Average Cost of Capital (WACC)
A3: All Amounts Denominated in INR MM Unless Otherwise Stated
A5: WACC Calculation
C7: Current Capital Structure
D8: Market Cap | H8: 648206.91
D9: Total Debt | H9: 14367.84
D10: Debt / Equity | H10: =H9/H8 -> 0.022165515
C12: Cost of Debt
D13: Pre-Tax Cost of Debt | H13: =H10 -> 0.022165515
D14: Tax Rate | H14: =[2]Model!E133 -> 0.1568
D15: After-Tax Cost of Debt | H15: =H13*(1-H14) -> 0.018689962
C17: Cost of Equity
D18: Risk Free Rate | H18: 0.06588
D19: Equity Market Return | H19: 0.12321276
D20: Equity Risk Premium | H20: =H19-H18 -> 0.057332763
D21: Levered Equity Beta | H21: =Beta!H9 -> 0.58533231
D22: Cost of Equity | H22: =H18+(H20*H21) -> 0.099438718
D24: WACC | H24: =(H15*H10)+(H22*(1-H10)) -> 0.097648881

Sheet Beta
A1: =Historical!A1 -> Alkem Laboratories
A2: Company Beta
B4: Index | C4: % Change | D4: Stock | E4: % Change
A5: Date | B5: Close Price | C5: Monthly | D5: Close Price | E5: Monthly
A6: 45870 | B6: 15714.75 | C6: =B6/B7-1 -> -0.03069863 | D6: 5303.5 | E6: =D6/D7-1 -> 0.054143229
A7: 45839 | B7: 16212.45 | C7: =B7/B8-1 -> -0.03761976 | D7: 5031.1 | E7: =D7/D8-1 -> 0.018647499 | J7: Levered Beta | K7: =SLOPE(E6:E65,C6:C65) -> 0.44710975
A8: 45809 | B8: 16846.2 | C8: =B8/B9-1 -> 0.052959891 | D8: 4939 | E8: =D8/D9-1 -> -0.031283711 | J8: Weight | K8: 0.75
A9: 45778 | B9: 15998.9 | C9: =B9/B10-1 -> 0.04471696 | D9: 5098.5 | E9: =D9/D10-1 -> -0.0034206411 | G9: Adjusted Beta | H9: =(K7*K8)+(K10*K11) -> 0.58533231
A10: 45748 | B10: 15314.1 | C10: =B10/B11-1 -> 0.051677014 | D10: 5116 | E10: =D10/D11-1 -> 0.047995575 | J10: Market Beta | K10: 1
A11: 45717 | B11: 14561.6 | C11: =B11/B12-1 -> 0.075438603 | D11: 4881.7 | E11: =D11/D12-1 -> 0.050686583 | J11: Weight | K11: 0.25
A12: 45689 | B12: 13540.15 | C12: =B12/B13-1 -> -0.094189228 | D12: 4646.2 | E12: =D12/D13-1 -> -0.082331796
A13: 45658 | B13: 14948.1 | C13: =B13/B14-1 -> -0.064228971 | D13: 5063.05 | E13: =D13/D14-1 -> -0.10132413 | H13: SUMMARY OUTPUT
A14: 45627 | B14: 15974.1 | C14: =B14/B15-1 -> 0.017604434 | D14: 5633.9 | E14: =D14/D15-1 -> -0.0015152992
A15: 45597 | B15: 15697.75 | C15: =B15/B16-1 -> 0.010177225 | D15: 5642.45 | E15: =D15/D16-1 -> -0.023670892 | H15: Regression Statistics
A16: 45566 | B16: 15539.6 | C16: =B16/B17-1 -> -0.079590247 | D16: 5779.25 | E16: =D16/D17-1 -> -0.04519396 | H16: Multiple R | I16: 0.40346812
A17: 45536 | B17: 16883.35 | C17: =B17/B18-1 -> 0.015918719 | D17: 6052.8 | E17: =D17/D18-1 -> -0.019050783 | H17: R Square | I17: 0.16278653
A18: 45505 | B18: 16618.8 | C18: =B18/B19-1 -> -0.0025717741 | D18: 6170.35 | E18: =D18/D19-1 -> 0.16213391 | H18: Adjusted R Square | I18: 0.14809857
A19: 45474 | B19: 16661.65 | C19: =B19/B20-1 -> 0.060498436 | D19: 5309.5 | E19: =D19/D20-1 -> 0.063740271 | H19: Standard Error | I19: 0.065805166
A20: 45444 | B20: 15711.15 | C20: =B20/B21-1 -> 0.087769889 | D20: 4991.35 | E20: =D20/D21-1 -> 0.037605629 | H20: Observations | I20: 59
A21: 45413 | B21: 14443.45 | C21: =B21/B22-1 -> 0.019880807 | D21: 4810.45 | E21: =D21/D22-1 -> -0.0046761362
A22: 45383 | B22: 14161.9 | C22: =B22/B23-1 -> 0.046974458 | D22: 4833.05 | E22: =D22/D23-1 -> -0.02204573 | H22: ANOVA
A23: 45352 | B23: 13526.5 | C23: =B23/B24-1 -> -0.015957544 | D23: 4942 | E23: =D23/D24-1 -> -0.036149278 | I23: df | J23: SS | K23: MS | L23: F | M23: Significance F
A24: 45323 | B24: 13745.85 | C24: =B24/B25-1 -> 0.0091956301 | D24: 5127.35 | E24: =D24/D25-1 -> 0.026280762 | H24: Regression | I24: 1 | J24: 0.04799291 | K24: 0.04799291 | L24: 11.082994 | M24: 0.001531429
A25: 45292 | B25: 13620.6 | C25: =B25/B26-1 -> 0.036184999 | D25: 4996.05 | E25: =D25/D26-1 -> -0.039701303 | H25: Residual | I25: 57 | J25: 0.24682823 | K25: 0.0043303199
A26: 45261 | B26: 13144.95 | C26: =B26/B27-1 -> 0.077401931 | D26: 5202.6 | E26: =D26/D27-1 -> 0.10141737 | H26: Total | I26: 58 | J26: 0.29482114
A27: 45231 | B27: 12200.6 | C27: =B27/B28-1 -> 0.10224639 | D27: 4723.55 | E27: =D27/D28-1 -> 0.26914035
A28: 45200 | B28: 11068.85 | C28: =B28/B29-1 -> -0.046746156 | D28: 3721.85 | E28: =D28/D29-1 -> 0.032155634 | I28: Coefficients | J28: Standard Error | K28: t Stat | L28: P-value | M28: Lower 95% | N28: Upper 95% | O28: Lower 95.0% | P28: Upper 95.0%
A29: 45170 | B29: 11611.65 | C29: =B29/B30-1 -> 0.038363 | D29: 3605.9 | E29: =D29/D30-1 -> -0.010143157 | H29: Intercept | I29: 0.0033289726 | J29: 0.0091001851 | K29: 0.36581373 | L29: 0.71585823 | M29: -0.014893834 | N29: 0.021551779 | O29: -0.014893834 | P29: 0.021551779
A30: 45139 | B30: 11182.65 | C30: =B30/B31-1 -> 0.033277893 | D30: 3642.85 | E30: =D30/D31-1 -> -0.0844235 | H30: X Variable 1 | I30: 0.73090413 | J30: 0.2195492 | K30: 3.3291131 | L30: 0.001531429 | M30: 0.29126443 | N30: 1.1705438 | O30: 0.29126443 | P30: 1.1705438
A31: 45108 | B31: 10822.5 | C31: =B31/B32-1 -> 0.068693621 | D31: 3978.75 | E31: =D31/D32-1 -> 0.13262735
A32: 45078 | B32: 10126.85 | C32: =B32/B33-1 -> 0.061525802 | D32: 3512.85 | E32: =D32/D33-1 -> 0.045615549
A33: 45047 | B33: 9539.9 | C33: =B33/B34-1 -> 0.064382423 | D33: 3359.6 | E33: =D33/D34-1 -> -0.042821733
A34: 45017 | B34: 8962.85 | C34: =B34/B35-1 -> 0.05858766 | D34: 3509.9 | E34: =D34/D35-1 -> 0.033509025
A35: 44986 | B35: 8466.8 | C35: =B35/B36-1 -> 0.0011943193 | D35: 3396.1 | E35: =D35/D36-1 -> 0.069637795
A36: 44958 | B36: 8456.7 | C36: =B36/B37-1 -> -0.020988655 | D36: 3175 | E36: =D36/D37-1 -> 0.06239167
A37: 44927 | B37: 8638 | C37: =B37/B38-1 -> -0.012997401 | D37: 2988.54 | E37: =D37/D38-1 -> 0.0021965198
A38: 44896 | B38: 8751.75 | C38: =B38/B39-1 -> -0.011727043 | D38: 2981.99 | E38: =D38/D39-1 -> -0.038250785
A39: 44866 | B39: 8855.6 | C39: =B39/B40-1 -> 0.019015345 | D39: 3100.59 | E39: =D39/D40-1 -> -0.0098232392
A40: 44835 | B40: 8690.35 | C40: =B40/B41-1 -> 0.042921262 | D40: 3131.35 | E40: =D40/D41-1 -> -0.03722755
A41: 44805 | B41: 8332.7 | C41: =B41/B42-1 -> -0.026098644 | D41: 3252.43 | E41: =D41/D42-1 -> 0.10170823
A42: 44774 | B42: 8556 | C42: =B42/B43-1 -> 0.047143487 | D42: 2952.17 | E42: =D42/D43-1 -> -0.077668811
... A64: 44105 | B64: 4666.05 | C64: =B64/B65-1 -> -0.00010714554 | D64: 2614.39 | E64: =D64/D65-1 -> -0.051709316
A65: 44075 | B65: 4666.55 | C65: 0 | D65: 2756.95 | E65: 0

Sheet Ratio Analysis
B1: Ratio Analysis (Actual, Forecasted, Peers)
D2: Actuals | I2: Forecasted | N2: Dr. Reddy's Laboratories Limited | O2: Torrent Pharmaceuticals Limited
B3: Particulars | D3: 2021 | E3: =D3+1 -> 2022 | F3: =E3+1 -> 2023 | G3: =F3+1 -> 2024 | H3: =G3+1 -> 2025 | I3: =H3+1 -> 2026 | J3: =I3+1 -> 2027 | K3: =J3+1 -> 2028 | L3: =K3+1 -> 2029 | M3: =L3+1 -> 2030 | N3: 2025 | O3: 2025
B5: Liquidity Ratios
B6: Current Ratio | D6: =SUM(Model!H45:H49)/SUM(Model!H60:H61) -> 3.3853884 | E6: =SUM(Model!I45:I49)/SUM(Model!I60:I61) -> 3.6606371 | F6: =SUM(Model!J45:J49)/SUM(Model!J60:J61) -> 3.3991759 | G6: =SUM(Model!K45:K49)/SUM(Model!K60:K61) -> 2.610437 | H6: =SUM(Model!L45:L49)/SUM(Model!L60:L61) -> 2.4615436 | I6: =SUM(Model!M45:M49)/SUM(Model!M60:M61) -> 3.0166276 | J6: =SUM(Model!N45:N49)/SUM(Model!N60:N61) -> 3.4694735 | K6: =SUM(Model!O45:O49)/SUM(Model!O60:O61) -> 3.9392902 | ... M6: =SUM(Model!Q45:Q49)/SUM(Model!Q60:Q61) -> 4.9235978 | N6: =250181/130338 -> 1.9194786 | O6: 1.46
B7: Quick Ratio | D7: =(SUM(Model!H45:H49)-Model!H48)/SUM(Model!H60:H61) -> 2.1745029 | E7: =(SUM(Model!I45:I49)-Model!I48)/SUM(Model!I60:I61) -> 2.3025124 | F7: =(SUM(Model!J45:J49)-Model!J48)/SUM(Model!J60:J61) -> 2.303934 | G7: =(SUM(Model!K45:K49)-Model!K48)/SUM(Model!K60:K61) -> 1.661845 | H7: =(SUM(Model!L45:L49)-Model!L48)/SUM(Model!L60:L61) -> 1.5374351 | I7: =(SUM(Model!M45:M49)-Model!M48)/SUM(Model!M60:M61) -> 1.8988301 | J7: =(SUM(Model!N45:N49)-Model!N48)/SUM(Model!N60:N61) -> 2.3113364 | K7: =(SUM(Model!O45:O49)-Model!O48)/SUM(Model!O60:O61) -> 2.7463702 | ... M7: =(SUM(Model!Q45:Q49)-Model!Q48)/SUM(Model!Q60:Q61) -> 3.67495 | N7: =(250181-71085)/130338 -> 1.3740889 | O7: 0.94
B8: Cash Ratio | D8: =(Model!H45+Model!H46)/SUM(Model!H60:H61) -> 1.0422787 | E8: =(Model!I45+Model!I46)/SUM(Model!I60:I61) -> 1.1651966 | F8: =(Model!J45+Model!J46)/SUM(Model!J60:J61) -> 1.0991734 | G8: =(Model!K45+Model!K46)/SUM(Model!K60:K61) -> 0.56296785 | H8: =(Model!L45+Model!L46)/SUM(Model!L60:L61) -> 0.49426861 | I8: =(Model!M45+Model!M46)/SUM(Model!M60:M61) -> 0.78468915 | J8: =(Model!N45+Model!N46)/SUM(Model!N60:N61) -> 1.1797001 | K8: =(Model!O45+Model!O46)/SUM(Model!O60:O61) -> 1.5996486 | ... M8: =(Model!Q45+Model!Q46)/SUM(Model!Q60:Q61) -> 2.5040593 | N8: =(14654+9948)/130338 -> 0.18875539 | O8: =580/4717 -> 0.12295951
B10: Solvency Ratio
B11: Debt to Equity | D11: =Model!H63/Model!H69 -> 0.24292335 | E11: =Model!I63/Model!I69 -> 0.30889337 | F11: =Model!J63/Model!J69 -> 0.15440964 | G11: =Model!K63/Model!K69 -> 0.13754866 | H11: =Model!L63/Model!L69 -> 0.11522027 | I11: =Model!M63/Model!M69 -> 0.10229333 | J11: =Model!N63/Model!N69 -> 0.090993898 | K11: =Model!O63/Model!O69 -> 0.081194354 | ... M11: =Model!Q63/Model!Q69 -> 0.065435531 | N11: 0.12 | O11: 0.34
B12: Interest Coverage | D12: =Model!H33/-Model!H34 -> 28.306348 | E12: =Model!I33/-Model!I34 -> 33.396219 | F12: =Model!J33/-Model!J34 -> 12.099758 | G12: =Model!K33/-Model!K34 -> 17.313317 | H12: =Model!L33/-Model!L34 -> 17.707395 | I12: =Model!M33/-Model!M34 -> 28.150355 | J12: =Model!N33/-Model!N34 -> 31.117599 | K12: =Model!O33/-Model!O34 -> 33.969447 | ... M12: =Model!Q33/-Model!Q34 -> 39.22184 | N12: 34.09 | O12: =(2697+252.31)/252.31 -> 11.689232
B13: Proprietry Ratio | D13: =Model!H69/Model!H56 -> 0.64038228 | E13: =Model!I69/Model!I56 -> 0.61395859 | F13: =Model!J69/Model!J56 -> 0.65752223 | G13: =Model!K69/Model!K56 -> 0.66209478 | H13: =Model!L69/Model!L56 -> 0.67745194 | I13: =Model!M69/Model!M56 -> 0.70587566 | J13: =Model!N69/Model!N56 -> 0.72417612 | K13: =Model!O69/Model!O56 -> 0.74156441 | ... M13: =Model!Q69/Model!Q56 -> 0.77313346 | N13: =339274/494226 -> 0.68647542 | O13: =7590.69/14989.74 -> 0.50639237
B15: Activity Ratios
B16: Receivables Turnover Ratio | D16: =Model!H25/Model!H47 -> 5.5157758 | E16: =Model!I25/Model!I47 -> 5.6426775 | F16: =Model!J25/Model!J47 -> 5.4400942 | G16: =Model!K25/Model!K47 -> 5.623013 | H16: =Model!L25/Model!L47 -> 5.2567745 | I16: =Model!M25/Model!M47 -> 5.4920271 | J16: =Model!N25/Model!N47 -> 5.4920271 | K16: =Model!O25/Model!O47 -> 5.4920271 | ... M16: =Model!Q25/Model!Q47 -> 5.4920271 | N16: =326439/90420 -> 3.6102522 | O16: =11539.36/(1855) -> 6.2206792
B17: No. of receivables days | D17: =365/D16 -> 66.173828 | E17: =365/E16 -> 64.685604 | F17: =365/F16 -> 67.094427 | G17: =365/G16 -> 64.911818 | H17: =365/H16 -> 69.434214 | I17: =365/I16 -> 66.459978 | J17: =365/J16 -> 66.459978 | K17: =365/K16 -> 66.459978 | ... O17: =365/O16 -> 58.675264
B18: Inventory Turnover | D18: =-Model!H26/(AVERAGE(Model!G48:H48)) -> 1.5128868 | E18: =-Model!I26/(AVERAGE(Model!H48:I48)) -> 1.5721375 | F18: =-Model!J26/(AVERAGE(Model!I48:J48)) -> 1.7483654 | G18: =-Model!K26/(AVERAGE(Model!J48:K48)) -> 1.8743032 | H18: =-Model!L26/(AVERAGE(Model!K48:L48)) -> 1.7065221 | I18: =-Model!M26/(AVERAGE(Model!L48:M48)) -> 1.7657149 | J18: =-Model!N26/(AVERAGE(Model!M48:N48)) -> 1.7009804 | K18: =-Model!O26/(AVERAGE(Model!N48:O48)) -> 1.6923437 | ... M18: =-Model!Q26/(AVERAGE(Model!P48:Q48)) -> 1.6780868 | N18: 0.84 | O18: 6.07
B19: No. of Inventory Days | D19: =365/D18 -> 241.26061 | E19: =365/E18 -> 232.16799 | F19: =365/F18 -> 208.76643 | G19: =365/G18 -> 194.73904 | H19: =365/H18 -> 213.8853 | I19: =365/I18 -> 206.71514 | J19: =365/J18 -> 214.58213 | K19: =365/K18 -> 215.67723 | ... O19: =365/O18 -> 60.131796
B20: Asset Turnover Ratio | D20: =Model!H25/AVERAGE(Model!G55:H56) -> 1.3959898 | E20: =Model!I25/AVERAGE(Model!H55:I56) -> 1.5077509 | F20: =Model!J25/AVERAGE(Model!I55:J56) -> 1.5122397 | G20: =Model!K25/AVERAGE(Model!J55:K56) -> 1.5628626 | H20: =Model!L25/AVERAGE(Model!K55:L56) -> 1.4065401 | I20: =Model!M25/AVERAGE(Model!L55:M56) -> 1.4045401 | J20: =Model!N25/AVERAGE(Model!M55:N56) -> 1.4149373 | K20: =Model!O25/AVERAGE(Model!N55:O56) -> 1.4020148 | ... M20: =Model!Q25/AVERAGE(Model!P55:Q56) -> 1.3444956 | N20: 0.74 | O20: 0.77
B21: Payables Turnover Ratio | D21: =-Model!H26/AVERAGE(Model!G60:H60) -> 3.2713926 | E21: =-Model!I26/AVERAGE(Model!H60:I60) -> 3.7277587 | F21: =-Model!J26/AVERAGE(Model!I60:J60) -> 4.1967679 | G21: =-Model!K26/AVERAGE(Model!J60:K60) -> 3.3898796 | H21: =-Model!L26/AVERAGE(Model!K60:L60) -> 2.6560557 | I21: =-Model!M26/AVERAGE(Model!L60:M60) -> 3.1248561 | J21: =-Model!N26/AVERAGE(Model!M60:N60) -> 3.3322507 | K21: =-Model!O26/AVERAGE(Model!N60:O60) -> 3.3153312 | ... M21: =-Model!Q26/AVERAGE(Model!P60:Q60) -> 3.2874017 | N21: =(56835+48411)/(210+26268) -> 3.974847 | O21: =(1520+1530)/1920 -> 1.5885417
B22: No. of payables days | D22: =365/D21 -> 111.57328 | E22: =365/E21 -> 97.914062 | F22: =365/F21 -> 86.971692 | G22: =365/G21 -> 107.67344 | H22: =365/H21 -> 137.42182 | I22: =365/I21 -> 116.80538 | J22: =365/J21 -> 109.53558 | K22: =365/K21 -> 110.09458 | ... O22: =365/O21 -> 229.77049
B23: Working Capital Ratio | D23: =SUM(Model!H45:H49)/SUM(Model!H60:H61) -> 3.3853884 | E23: =SUM(Model!I45:I49)/SUM(Model!I60:I61) -> 3.6606371 | F23: =SUM(Model!J45:J49)/SUM(Model!J60:J61) -> 3.3991759 | G23: =SUM(Model!K45:K49)/SUM(Model!K60:K61) -> 2.610437 | H23: =SUM(Model!L45:L49)/SUM(Model!L60:L61) -> 2.4615436 | I23: =SUM(Model!M45:M49)/SUM(Model!M60:M61) -> 3.0166276 | J23: =SUM(Model!N45:N49)/SUM(Model!N60:N61) -> 3.4694735 | K23: =SUM(Model!O45:O49)/SUM(Model!O60:O61) -> 3.9392902 | ... M23: =SUM(Model!Q45:Q49)/SUM(Model!Q60:Q61) -> 4.9235978 | N23: =250181/130338 -> 1.9194786 | O23: 1.46
B25: Profitability Ratios
B26: Net Profit Margin | D26: =Model!H38/Model!H25 -> 0.18248936 | E26: =Model!I38/Model!I25 -> 0.15801109 | F26: =Model!J38/Model!J25 -> 0.086799503 | G26: =Model!K38/Model!K25 -> 0.14299969 | H26: =Model!L38/Model!L25 -> 0.17092804 | I26: =Model!M38/Model!M25 -> 0.15195181 | J26: =Model!N38/Model!N25 -> 0.15454125 | K26: =Model!O38/Model!O25 -> 0.15681237 | ... M26: =Model!Q38/Model!Q25 -> 0.16056478 | N26: 0.1747 | O26: 0.1949
B27: EBIDTA Margin | D27: =Model!H31/Model!H25 -> 0.21910748 | E27: =Model!I31/Model!I25 -> 0.19304902 | F27: =Model!J31/Model!J25 -> 0.13875454 | G27: =Model!K31/Model!K25 -> 0.17726274 | H27: =Model!L31/Model!L25 -> 0.19377115 | I27: =Model!M31/Model!M25 -> 0.18438899 | J27: =Model!N31/Model!N25 -> 0.18438899 | K27: =Model!O31/Model!O25 -> 0.18438899 | ... M27: =Model!Q31/Model!Q25 -> 0.18438899 | N27: 0.2954 | O27: 0.3725
B28: ROA | D28: =Model!H38/AVERAGE(Model!G56:H56) -> 0.14044044 | E28: =Model!I38/AVERAGE(Model!H56:I56) -> 0.13133425 | F28: =Model!J38/AVERAGE(Model!I56:J56) -> 0.072365163 | G28: =Model!K38/AVERAGE(Model!J56:K56) -> 0.12351623 | H28: =Model!L38/AVERAGE(Model!K56:L56) -> 0.13322912 | I28: =Model!M38/AVERAGE(Model!L56:M56) -> 0.11787814 | J28: =Model!N38/AVERAGE(Model!M56:N56) -> 0.11984243 | K28: =Model!O38/AVERAGE(Model!N56:O56) -> 0.11957576 | ... M28: =Model!Q38/AVERAGE(Model!P56:Q56) -> 0.11588343 | N28: 0.1144 | O28: 0.147
B29: EPS | D29: =Model!H38/Model!$E$137 -> 135.29899 | E29: =Model!I38/Model!$E$137 -> 140.53023 | F29: =Model!J38/Model!$E$137 -> 84.202559 | G29: =Model!K38/Model!$E$137 -> 151.49787 | H29: =Model!L38/Model!$E$137 -> 185.33077 | I29: =Model!M38/Model!$E$137 -> 181.47264 | J29: =Model!N38/Model!$E$137 -> 200.85772 | K29: =Model!O38/Model!$E$137 -> 219.46198 | ... M29: =Model!Q38/Model!$E$137 -> 253.66323 | N29: 67.89 | O29: 55.79
B30: ROE | D30: =Model!H38/Model!H69 -> 0.2193072 | E30: =Model!I38/Model!I69 -> 0.19452876 | F30: =Model!J38/Model!J69 -> 0.11130765 | G30: =Model!K38/Model!K69 -> 0.17566422 | H30: =Model!L38/Model!L69 -> 0.18489979 | I30: =Model!M38/Model!M69 -> 0.16073797 | J30: =Model!N38/Model!N69 -> 0.15825622 | K30: =Model!O38/Model!O69 -> 0.15429261 | ... M30: =Model!Q38/Model!Q69 -> 0.14372461 | N30: 0.1685 | O30: 24.86
B32: Performance Ratios
B33: CFO to Revenue | D33: =Model!H82/Model!H25 -> 0.14268455 | E33: =Model!I82/Model!I25 -> 0.10447622 | F33: =Model!J82/Model!J25 -> 0.14505236 | G33: =Model!K82/Model!K25 -> 0.15378391 | H33: =Model!L82/Model!L25 -> 0.14754422 | I33: =Model!M82/Model!M25 -> 0.10940984 | J33: =Model!N82/Model!N25 -> 0.13626334 | K33: =Model!O82/Model!O25 -> 0.13885321 | ... M33: =Model!Q82/Model!Q25 -> 0.14319406 | N33: =46428/326439 -> 0.14222565 | O33: =2585.11/11539.36 -> 0.22402542
B34: CFO to Assets | D34: =Model!H82/Model!H56 -> 0.1098074 | E34: =Model!I82/Model!I56 -> 0.078968299 | F34: =Model!J82/Model!J56 -> 0.12230466 | G34: =Model!K82/Model!K56 -> 0.12507753 | H34: =Model!L82/Model!L56 -> 0.10812442 | I34: =Model!M82/Model!M56 -> 0.081695326 | J34: =Model!N82/Model!N56 -> 0.10105076 | K34: =Model!O82/Model!O56 -> 0.10131404 | ... M34: =Model!Q82/Model!Q56 -> 0.099096959 | N34: =46428/494266 -> 0.093933226 | O34: =2585.11/14989.74 -> 0.17245863
B35: CFO to Operating Income | D35: =Model!H82/Model!H33 -> 0.75841972 | E35: =Model!I82/Model!I33 -> 0.63524609 | F35: =Model!J82/Model!J33 -> 1.2951972 | G35: =Model!K82/Model!K33 -> 1.000966 | H35: =Model!L82/Model!L33 -> 0.88763289 | I35: =Model!M82/Model!M33 -> 0.68195237 | J35: =Model!N82/Model!N33 -> 0.83616749 | K35: =Model!O82/Model!O33 -> 0.84047086 | ... M35: =Model!Q82/Model!Q33 -> 0.84738448 | N35: =46428/(76578+2829) -> 0.58468397 | O35: =2585.11/(2697+252.31) -> 0.87651349

Sheet DuPont
B4: DUPONT ANALYSIS
D5: Actuals | I5: Forecasted
B6: Particulars | D6: 2021A | E6: 2022A | F6: 2023A | G6: 2024A | H6: 2025A | I6: 2026F | J6: 2027F | K6: 2028F | L6: 2029F | M6: 2030F
B8: Net profit Margin | D8: =Model!H38/Model!H25 -> 0.18248936 | E8: =Model!I38/Model!I25 -> 0.15801109 | F8: =Model!J38/Model!J25 -> 0.086799503 | G8: =Model!K38/Model!K25 -> 0.14299969 | H8: =Model!L38/Model!L25 -> 0.17092804 | I8: =Model!M38/Model!M25 -> 0.15195181 | J8: =Model!N38/Model!N25 -> 0.15454125 | K8: =Model!O38/Model!O25 -> 0.15681237 | ... M8: =Model!Q38/Model!Q25 -> 0.16056478
B9: Asset Turnover | D9: ='Ratio Analysis'!D20 -> 1.3959898 | E9: ='Ratio Analysis'!E20 -> 1.5077509 | F9: ='Ratio Analysis'!F20 -> 1.5122397 | G9: ='Ratio Analysis'!G20 -> 1.5628626 | H9: ='Ratio Analysis'!H20 -> 1.4065401 | I9: ='Ratio Analysis'!I20 -> 1.4045401 | J9: ='Ratio Analysis'!J20 -> 1.4149373 | K9: ='Ratio Analysis'!K20 -> 1.4020148 | ... M9: ='Ratio Analysis'!M20 -> 1.3444956
B10: Equity Multiplier | D10: 0.86086111 | E10: 0.81651964 | F10: 0.84798304 | G10: 0.78600881 | H10: 0.76907906 | I10: 0.75314475 | J10: 0.72373433 | K10: 0.70179816 | L10: 0.68257425 | M10: 0.66576579
B12: ROE | D12: =D8*D9*D10 -> 0.2193072 | E12: =E8*E9*E10 -> 0.19452876 | F12: =F8*F9*F10 -> 0.11130765 | G12: =G8*G9*G10 -> 0.17566422 | H12: =H8*H9*H10 -> 0.18489979 | I12: =I8*I9*I10 -> 0.16073797 | J12: =J8*J9*J10 -> 0.15825622 | K12: =K8*K9*K10 -> 0.15429261 | ... M12: =M8*M9*M10 -> 0.14372461
